{"sprites":[{"active":true,"name":"square-brick-03.png","description":"__","gravity":"medium","__initializers":[],"img":{},"src":"http://localhost:3137/assets/uploads/square-brick-03.png","__mapScale":false,"__mapSize":{"x":200,"y":200,"z":0},"frameSize":{"x":200,"y":200,"z":0},"type":"basic","animations":[{"defaultArgs":{"name":"my-animation","description":"my-description","frames":[],"type":"none","delay":0,"frameSize":{"x":44,"y":44,"z":0},"frameBounds":{"min":{"x":0,"y":0,"z":0},"max":{"x":0,"y":0,"z":0},"termPoint":{"x":0,"y":0,"z":0}},"frameOffset":{"x":0,"y":0,"z":0},"flipX":false,"duration":1000,"size":{"x":20,"y":20,"z":20}},"name":"my-animation","description":"my-description","image":{"image":{},"src":"http://localhost:3137/assets/uploads/square-brick-03.png","domElement":{}},"src":"http://localhost:3137/assets/uploads/square-brick-03.png","domElement":{},"frameSize":{"x":200,"y":200,"z":0},"frameBounds":{"min":{"x":0,"y":0,"z":0},"max":{"x":0,"y":0,"z":0},"termPoint":{"x":0,"y":0,"z":0}},"frameOffset":{"x":0,"y":0,"z":0},"extras":false,"frames":[{"image":{"image":{},"src":"http://localhost:3137/assets/uploads/square-brick-03.png","domElement":{}},"frameSize":{"x":200,"y":200,"z":0},"framePos":{"x":0,"y":0}}],"flipX":false,"cix":0,"selected_frame":{"image":{"image":{},"src":"http://localhost:3137/assets/uploads/square-brick-03.png","domElement":{}},"frameSize":{"x":200,"y":200,"z":0},"framePos":{"x":0,"y":0}},"timer":0,"duration":1000,"seesaw_mode":false}],"motions":[],"projectiles":[],"sounds":[],"image":{"image":{},"src":"http://localhost:3137/assets/uploads/square-brick-03.png","domElement":{}},"size":{"x":200,"y":200,"z":0},"position":{"x":0,"y":4750,"z":0},"collision_bounds":{"min":{"x":0,"y":0,"z":0},"max":{"x":0,"y":0,"z":0}},"rotation":{"x":0,"y":0,"z":0},"selected_animation":{"defaultArgs":{"name":"my-animation","description":"my-description","frames":[],"type":"none","delay":0,"frameSize":{"x":44,"y":44,"z":0},"frameBounds":{"min":{"x":0,"y":0,"z":0},"max":{"x":0,"y":0,"z":0},"termPoint":{"x":0,"y":0,"z":0}},"frameOffset":{"x":0,"y":0,"z":0},"flipX":false,"duration":1000,"size":{"x":20,"y":20,"z":20}},"name":"my-animation","description":"my-description","image":{"image":{},"src":"http://localhost:3137/assets/uploads/square-brick-03.png","domElement":{}},"src":"http://localhost:3137/assets/uploads/square-brick-03.png","domElement":{},"frameSize":{"x":200,"y":200,"z":0},"frameBounds":{"min":{"x":0,"y":0,"z":0},"max":{"x":0,"y":0,"z":0},"termPoint":{"x":0,"y":0,"z":0}},"frameOffset":{"x":0,"y":0,"z":0},"extras":false,"frames":[{"image":{"image":{},"src":"http://localhost:3137/assets/uploads/square-brick-03.png","domElement":{}},"frameSize":{"x":200,"y":200,"z":0},"framePos":{"x":0,"y":0}}],"flipX":false,"cix":0,"selected_frame":{"image":{"image":{},"src":"http://localhost:3137/assets/uploads/square-brick-03.png","domElement":{}},"frameSize":{"x":200,"y":200,"z":0},"framePos":{"x":0,"y":0}},"timer":0,"duration":1000,"seesaw_mode":false},"speed":{"x":0,"y":0,"z":0},"acceleration":{"x":0,"y":0,"z":0},"rot_speed":{"x":0,"y":0,"z":0},"rot_accel":{"x":0,"y":0,"z":0},"padding":{"x":0,"y":0,"z":0},"tag":"square-brick-03.png","mapSize":{"x":200,"y":200,"z":0},"id":"80944f58-6144-4a83-a4df-1035ee8915e1","hoverSelected":false,"hover_selected":false,"drag_selected":false,"selected":false},{"active":true,"name":"square-brick-03.png","description":"__","gravity":"medium","__initializers":[],"img":{},"src":"http://localhost:3137/assets/uploads/square-brick-03.png","__mapScale":false,"__mapSize":{"x":200,"y":200,"z":0},"frameSize":{"x":200,"y":200,"z":0},"type":"basic","animations":[{"defaultArgs":{"name":"my-animation","description":"my-description","frames":[],"type":"none","delay":0,"frameSize":{"x":44,"y":44,"z":0},"frameBounds":{"min":{"x":0,"y":0,"z":0},"max":{"x":0,"y":0,"z":0},"termPoint":{"x":0,"y":0,"z":0}},"frameOffset":{"x":0,"y":0,"z":0},"flipX":false,"duration":1000,"size":{"x":20,"y":20,"z":20}},"name":"my-animation","description":"my-description","image":{"image":{},"src":"http://localhost:3137/assets/uploads/square-brick-03.png","domElement":{}},"src":"http://localhost:3137/assets/uploads/square-brick-03.png","domElement":{},"frameSize":{"x":200,"y":200,"z":0},"frameBounds":{"min":{"x":0,"y":0,"z":0},"max":{"x":0,"y":0,"z":0},"termPoint":{"x":0,"y":0,"z":0}},"frameOffset":{"x":0,"y":0,"z":0},"extras":false,"frames":[{"image":{"image":{},"src":"http://localhost:3137/assets/uploads/square-brick-03.png","domElement":{}},"frameSize":{"x":200,"y":200,"z":0},"framePos":{"x":0,"y":0}}],"flipX":false,"cix":0,"selected_frame":{"image":{"image":{},"src":"http://localhost:3137/assets/uploads/square-brick-03.png","domElement":{}},"frameSize":{"x":200,"y":200,"z":0},"framePos":{"x":0,"y":0}},"timer":0,"duration":1000,"seesaw_mode":false}],"motions":[],"projectiles":[],"sounds":[],"image":{"image":{},"src":"http://localhost:3137/assets/uploads/square-brick-03.png","domElement":{}},"size":{"x":200,"y":200,"z":0},"position":{"x":200,"y":4750,"z":0},"collision_bounds":{"min":{"x":0,"y":0,"z":0},"max":{"x":0,"y":0,"z":0}},"rotation":{"x":0,"y":0,"z":0},"selected_animation":{"defaultArgs":{"name":"my-animation","description":"my-description","frames":[],"type":"none","delay":0,"frameSize":{"x":44,"y":44,"z":0},"frameBounds":{"min":{"x":0,"y":0,"z":0},"max":{"x":0,"y":0,"z":0},"termPoint":{"x":0,"y":0,"z":0}},"frameOffset":{"x":0,"y":0,"z":0},"flipX":false,"duration":1000,"size":{"x":20,"y":20,"z":20}},"name":"my-animation","description":"my-description","image":{"image":{},"src":"http://localhost:3137/assets/uploads/square-brick-03.png","domElement":{}},"src":"http://localhost:3137/assets/uploads/square-brick-03.png","domElement":{},"frameSize":{"x":200,"y":200,"z":0},"frameBounds":{"min":{"x":0,"y":0,"z":0},"max":{"x":0,"y":0,"z":0},"termPoint":{"x":0,"y":0,"z":0}},"frameOffset":{"x":0,"y":0,"z":0},"extras":false,"frames":[{"image":{"image":{},"src":"http://localhost:3137/assets/uploads/square-brick-03.png","domElement":{}},"frameSize":{"x":200,"y":200,"z":0},"framePos":{"x":0,"y":0}}],"flipX":false,"cix":0,"selected_frame":{"image":{"image":{},"src":"http://localhost:3137/assets/uploads/square-brick-03.png","domElement":{}},"frameSize":{"x":200,"y":200,"z":0},"framePos":{"x":0,"y":0}},"timer":0,"duration":1000,"seesaw_mode":false},"speed":{"x":0,"y":0,"z":0},"acceleration":{"x":0,"y":0,"z":0},"rot_speed":{"x":0,"y":0,"z":0},"rot_accel":{"x":0,"y":0,"z":0},"padding":{"x":0,"y":0,"z":0},"tag":"square-brick-03.png","mapSize":{"x":200,"y":200,"z":0},"id":"12978d51-9394-45c3-8a0f-588e3ada2541","hoverSelected":false,"hover_selected":false,"drag_selected":false,"selected":false},{"active":true,"name":"square-brick-03.png","description":"__","gravity":"medium","__initializers":[],"img":{},"src":"http://localhost:3137/assets/uploads/square-brick-03.png","__mapScale":false,"__mapSize":{"x":200,"y":200,"z":0},"frameSize":{"x":200,"y":200,"z":0},"type":"basic","animations":[{"defaultArgs":{"name":"my-animation","description":"my-description","frames":[],"type":"none","delay":0,"frameSize":{"x":44,"y":44,"z":0},"frameBounds":{"min":{"x":0,"y":0,"z":0},"max":{"x":0,"y":0,"z":0},"termPoint":{"x":0,"y":0,"z":0}},"frameOffset":{"x":0,"y":0,"z":0},"flipX":false,"duration":1000,"size":{"x":20,"y":20,"z":20}},"name":"my-animation","description":"my-description","image":{"image":{},"src":"http://localhost:3137/assets/uploads/square-brick-03.png","domElement":{}},"src":"http://localhost:3137/assets/uploads/square-brick-03.png","domElement":{},"frameSize":{"x":200,"y":200,"z":0},"frameBounds":{"min":{"x":0,"y":0,"z":0},"max":{"x":0,"y":0,"z":0},"termPoint":{"x":0,"y":0,"z":0}},"frameOffset":{"x":0,"y":0,"z":0},"extras":false,"frames":[{"image":{"image":{},"src":"http://localhost:3137/assets/uploads/square-brick-03.png","domElement":{}},"frameSize":{"x":200,"y":200,"z":0},"framePos":{"x":0,"y":0}}],"flipX":false,"cix":0,"selected_frame":{"image":{"image":{},"src":"http://localhost:3137/assets/uploads/square-brick-03.png","domElement":{}},"frameSize":{"x":200,"y":200,"z":0},"framePos":{"x":0,"y":0}},"timer":0,"duration":1000,"seesaw_mode":false}],"motions":[],"projectiles":[],"sounds":[],"image":{"image":{},"src":"http://localhost:3137/assets/uploads/square-brick-03.png","domElement":{}},"size":{"x":200,"y":200,"z":0},"position":{"x":400,"y":4750,"z":0},"collision_bounds":{"min":{"x":0,"y":0,"z":0},"max":{"x":0,"y":0,"z":0}},"rotation":{"x":0,"y":0,"z":0},"selected_animation":{"defaultArgs":{"name":"my-animation","description":"my-description","frames":[],"type":"none","delay":0,"frameSize":{"x":44,"y":44,"z":0},"frameBounds":{"min":{"x":0,"y":0,"z":0},"max":{"x":0,"y":0,"z":0},"termPoint":{"x":0,"y":0,"z":0}},"frameOffset":{"x":0,"y":0,"z":0},"flipX":false,"duration":1000,"size":{"x":20,"y":20,"z":20}},"name":"my-animation","description":"my-description","image":{"image":{},"src":"http://localhost:3137/assets/uploads/square-brick-03.png","domElement":{}},"src":"http://localhost:3137/assets/uploads/square-brick-03.png","domElement":{},"frameSize":{"x":200,"y":200,"z":0},"frameBounds":{"min":{"x":0,"y":0,"z":0},"max":{"x":0,"y":0,"z":0},"termPoint":{"x":0,"y":0,"z":0}},"frameOffset":{"x":0,"y":0,"z":0},"extras":false,"frames":[{"image":{"image":{},"src":"http://localhost:3137/assets/uploads/square-brick-03.png","domElement":{}},"frameSize":{"x":200,"y":200,"z":0},"framePos":{"x":0,"y":0}}],"flipX":false,"cix":0,"selected_frame":{"image":{"image":{},"src":"http://localhost:3137/assets/uploads/square-brick-03.png","domElement":{}},"frameSize":{"x":200,"y":200,"z":0},"framePos":{"x":0,"y":0}},"timer":0,"duration":1000,"seesaw_mode":false},"speed":{"x":0,"y":0,"z":0},"acceleration":{"x":0,"y":0,"z":0},"rot_speed":{"x":0,"y":0,"z":0},"rot_accel":{"x":0,"y":0,"z":0},"padding":{"x":0,"y":0,"z":0},"tag":"square-brick-03.png","mapSize":{"x":200,"y":200,"z":0},"id":"dd341410-d07a-47c6-b438-010147a623e0","hoverSelected":false,"hover_selected":false,"drag_selected":false,"selected":false},{"active":true,"name":"square-brick-03.png","description":"__","gravity":"medium","__initializers":[],"img":{},"src":"http://localhost:3137/assets/uploads/square-brick-03.png","__mapScale":false,"__mapSize":{"x":200,"y":200,"z":0},"frameSize":{"x":200,"y":200,"z":0},"type":"basic","animations":[{"defaultArgs":{"name":"my-animation","description":"my-description","frames":[],"type":"none","delay":0,"frameSize":{"x":44,"y":44,"z":0},"frameBounds":{"min":{"x":0,"y":0,"z":0},"max":{"x":0,"y":0,"z":0},"termPoint":{"x":0,"y":0,"z":0}},"frameOffset":{"x":0,"y":0,"z":0},"flipX":false,"duration":1000,"size":{"x":20,"y":20,"z":20}},"name":"my-animation","description":"my-description","image":{"image":{},"src":"http://localhost:3137/assets/uploads/square-brick-03.png","domElement":{}},"src":"http://localhost:3137/assets/uploads/square-brick-03.png","domElement":{},"frameSize":{"x":200,"y":200,"z":0},"frameBounds":{"min":{"x":0,"y":0,"z":0},"max":{"x":0,"y":0,"z":0},"termPoint":{"x":0,"y":0,"z":0}},"frameOffset":{"x":0,"y":0,"z":0},"extras":false,"frames":[{"image":{"image":{},"src":"http://localhost:3137/assets/uploads/square-brick-03.png","domElement":{}},"frameSize":{"x":200,"y":200,"z":0},"framePos":{"x":0,"y":0}}],"flipX":false,"cix":0,"selected_frame":{"image":{"image":{},"src":"http://localhost:3137/assets/uploads/square-brick-03.png","domElement":{}},"frameSize":{"x":200,"y":200,"z":0},"framePos":{"x":0,"y":0}},"timer":0,"duration":1000,"seesaw_mode":false}],"motions":[],"projectiles":[],"sounds":[],"image":{"image":{},"src":"http://localhost:3137/assets/uploads/square-brick-03.png","domElement":{}},"size":{"x":200,"y":200,"z":0},"position":{"x":600,"y":4750,"z":0},"collision_bounds":{"min":{"x":0,"y":0,"z":0},"max":{"x":0,"y":0,"z":0}},"rotation":{"x":0,"y":0,"z":0},"selected_animation":{"defaultArgs":{"name":"my-animation","description":"my-description","frames":[],"type":"none","delay":0,"frameSize":{"x":44,"y":44,"z":0},"frameBounds":{"min":{"x":0,"y":0,"z":0},"max":{"x":0,"y":0,"z":0},"termPoint":{"x":0,"y":0,"z":0}},"frameOffset":{"x":0,"y":0,"z":0},"flipX":false,"duration":1000,"size":{"x":20,"y":20,"z":20}},"name":"my-animation","description":"my-description","image":{"image":{},"src":"http://localhost:3137/assets/uploads/square-brick-03.png","domElement":{}},"src":"http://localhost:3137/assets/uploads/square-brick-03.png","domElement":{},"frameSize":{"x":200,"y":200,"z":0},"frameBounds":{"min":{"x":0,"y":0,"z":0},"max":{"x":0,"y":0,"z":0},"termPoint":{"x":0,"y":0,"z":0}},"frameOffset":{"x":0,"y":0,"z":0},"extras":false,"frames":[{"image":{"image":{},"src":"http://localhost:3137/assets/uploads/square-brick-03.png","domElement":{}},"frameSize":{"x":200,"y":200,"z":0},"framePos":{"x":0,"y":0}}],"flipX":false,"cix":0,"selected_frame":{"image":{"image":{},"src":"http://localhost:3137/assets/uploads/square-brick-03.png","domElement":{}},"frameSize":{"x":200,"y":200,"z":0},"framePos":{"x":0,"y":0}},"timer":0,"duration":1000,"seesaw_mode":false},"speed":{"x":0,"y":0,"z":0},"acceleration":{"x":0,"y":0,"z":0},"rot_speed":{"x":0,"y":0,"z":0},"rot_accel":{"x":0,"y":0,"z":0},"padding":{"x":0,"y":0,"z":0},"tag":"square-brick-03.png","mapSize":{"x":200,"y":200,"z":0},"id":"1469b65f-346f-4a49-94c2-e9c1b425f86d","hoverSelected":false,"hover_selected":false,"drag_selected":false,"selected":false},{"active":true,"name":"square-brick-03.png","description":"__","gravity":"medium","__initializers":[],"img":{},"src":"http://localhost:3137/assets/uploads/square-brick-03.png","__mapScale":false,"__mapSize":{"x":200,"y":200,"z":0},"frameSize":{"x":200,"y":200,"z":0},"type":"basic","animations":[{"defaultArgs":{"name":"my-animation","description":"my-description","frames":[],"type":"none","delay":0,"frameSize":{"x":44,"y":44,"z":0},"frameBounds":{"min":{"x":0,"y":0,"z":0},"max":{"x":0,"y":0,"z":0},"termPoint":{"x":0,"y":0,"z":0}},"frameOffset":{"x":0,"y":0,"z":0},"flipX":false,"duration":1000,"size":{"x":20,"y":20,"z":20}},"name":"my-animation","description":"my-description","image":{"image":{},"src":"http://localhost:3137/assets/uploads/square-brick-03.png","domElement":{}},"src":"http://localhost:3137/assets/uploads/square-brick-03.png","domElement":{},"frameSize":{"x":200,"y":200,"z":0},"frameBounds":{"min":{"x":0,"y":0,"z":0},"max":{"x":0,"y":0,"z":0},"termPoint":{"x":0,"y":0,"z":0}},"frameOffset":{"x":0,"y":0,"z":0},"extras":false,"frames":[{"image":{"image":{},"src":"http://localhost:3137/assets/uploads/square-brick-03.png","domElement":{}},"frameSize":{"x":200,"y":200,"z":0},"framePos":{"x":0,"y":0}}],"flipX":false,"cix":0,"selected_frame":{"image":{"image":{},"src":"http://localhost:3137/assets/uploads/square-brick-03.png","domElement":{}},"frameSize":{"x":200,"y":200,"z":0},"framePos":{"x":0,"y":0}},"timer":0,"duration":1000,"seesaw_mode":false}],"motions":[],"projectiles":[],"sounds":[],"image":{"image":{},"src":"http://localhost:3137/assets/uploads/square-brick-03.png","domElement":{}},"size":{"x":200,"y":200,"z":0},"position":{"x":800,"y":4750,"z":0},"collision_bounds":{"min":{"x":0,"y":0,"z":0},"max":{"x":0,"y":0,"z":0}},"rotation":{"x":0,"y":0,"z":0},"selected_animation":{"defaultArgs":{"name":"my-animation","description":"my-description","frames":[],"type":"none","delay":0,"frameSize":{"x":44,"y":44,"z":0},"frameBounds":{"min":{"x":0,"y":0,"z":0},"max":{"x":0,"y":0,"z":0},"termPoint":{"x":0,"y":0,"z":0}},"frameOffset":{"x":0,"y":0,"z":0},"flipX":false,"duration":1000,"size":{"x":20,"y":20,"z":20}},"name":"my-animation","description":"my-description","image":{"image":{},"src":"http://localhost:3137/assets/uploads/square-brick-03.png","domElement":{}},"src":"http://localhost:3137/assets/uploads/square-brick-03.png","domElement":{},"frameSize":{"x":200,"y":200,"z":0},"frameBounds":{"min":{"x":0,"y":0,"z":0},"max":{"x":0,"y":0,"z":0},"termPoint":{"x":0,"y":0,"z":0}},"frameOffset":{"x":0,"y":0,"z":0},"extras":false,"frames":[{"image":{"image":{},"src":"http://localhost:3137/assets/uploads/square-brick-03.png","domElement":{}},"frameSize":{"x":200,"y":200,"z":0},"framePos":{"x":0,"y":0}}],"flipX":false,"cix":0,"selected_frame":{"image":{"image":{},"src":"http://localhost:3137/assets/uploads/square-brick-03.png","domElement":{}},"frameSize":{"x":200,"y":200,"z":0},"framePos":{"x":0,"y":0}},"timer":0,"duration":1000,"seesaw_mode":false},"speed":{"x":0,"y":0,"z":0},"acceleration":{"x":0,"y":0,"z":0},"rot_speed":{"x":0,"y":0,"z":0},"rot_accel":{"x":0,"y":0,"z":0},"padding":{"x":0,"y":0,"z":0},"tag":"square-brick-03.png","mapSize":{"x":200,"y":200,"z":0},"id":"50ba1723-5c65-4549-a7ef-4fa1a6529fe2","hoverSelected":false,"hover_selected":false,"drag_selected":false,"selected":false},{"active":true,"name":"square-brick-02.png","description":"__","gravity":"medium","__initializers":[],"img":{},"src":"http://localhost:3137/assets/uploads/square-brick-02.png","__mapScale":false,"__mapSize":{"x":200,"y":200,"z":0},"frameSize":{"x":200,"y":200,"z":0},"type":"basic","animations":[{"defaultArgs":{"name":"my-animation","description":"my-description","frames":[],"type":"none","delay":0,"frameSize":{"x":44,"y":44,"z":0},"frameBounds":{"min":{"x":0,"y":0,"z":0},"max":{"x":0,"y":0,"z":0},"termPoint":{"x":0,"y":0,"z":0}},"frameOffset":{"x":0,"y":0,"z":0},"flipX":false,"duration":1000,"size":{"x":20,"y":20,"z":20}},"name":"my-animation","description":"my-description","image":{"image":{},"src":"http://localhost:3137/assets/uploads/square-brick-02.png","domElement":{}},"src":"http://localhost:3137/assets/uploads/square-brick-02.png","domElement":{},"frameSize":{"x":200,"y":200,"z":0},"frameBounds":{"min":{"x":0,"y":0,"z":0},"max":{"x":0,"y":0,"z":0},"termPoint":{"x":0,"y":0,"z":0}},"frameOffset":{"x":0,"y":0,"z":0},"extras":false,"frames":[{"image":{"image":{},"src":"http://localhost:3137/assets/uploads/square-brick-02.png","domElement":{}},"frameSize":{"x":200,"y":200,"z":0},"framePos":{"x":0,"y":0}}],"flipX":false,"cix":0,"selected_frame":{"image":{"image":{},"src":"http://localhost:3137/assets/uploads/square-brick-02.png","domElement":{}},"frameSize":{"x":200,"y":200,"z":0},"framePos":{"x":0,"y":0}},"timer":0,"duration":1000,"seesaw_mode":false}],"motions":[],"projectiles":[],"sounds":[],"image":{"image":{},"src":"http://localhost:3137/assets/uploads/square-brick-02.png","domElement":{}},"size":{"x":200,"y":200,"z":0},"position":{"x":1000,"y":4750,"z":0},"collision_bounds":{"min":{"x":0,"y":0,"z":0},"max":{"x":0,"y":0,"z":0}},"rotation":{"x":0,"y":0,"z":0},"selected_animation":{"defaultArgs":{"name":"my-animation","description":"my-description","frames":[],"type":"none","delay":0,"frameSize":{"x":44,"y":44,"z":0},"frameBounds":{"min":{"x":0,"y":0,"z":0},"max":{"x":0,"y":0,"z":0},"termPoint":{"x":0,"y":0,"z":0}},"frameOffset":{"x":0,"y":0,"z":0},"flipX":false,"duration":1000,"size":{"x":20,"y":20,"z":20}},"name":"my-animation","description":"my-description","image":{"image":{},"src":"http://localhost:3137/assets/uploads/square-brick-02.png","domElement":{}},"src":"http://localhost:3137/assets/uploads/square-brick-02.png","domElement":{},"frameSize":{"x":200,"y":200,"z":0},"frameBounds":{"min":{"x":0,"y":0,"z":0},"max":{"x":0,"y":0,"z":0},"termPoint":{"x":0,"y":0,"z":0}},"frameOffset":{"x":0,"y":0,"z":0},"extras":false,"frames":[{"image":{"image":{},"src":"http://localhost:3137/assets/uploads/square-brick-02.png","domElement":{}},"frameSize":{"x":200,"y":200,"z":0},"framePos":{"x":0,"y":0}}],"flipX":false,"cix":0,"selected_frame":{"image":{"image":{},"src":"http://localhost:3137/assets/uploads/square-brick-02.png","domElement":{}},"frameSize":{"x":200,"y":200,"z":0},"framePos":{"x":0,"y":0}},"timer":0,"duration":1000,"seesaw_mode":false},"speed":{"x":0,"y":0,"z":0},"acceleration":{"x":0,"y":0,"z":0},"rot_speed":{"x":0,"y":0,"z":0},"rot_accel":{"x":0,"y":0,"z":0},"padding":{"x":0,"y":0,"z":0},"tag":"square-brick-02.png","mapSize":{"x":200,"y":200,"z":0},"id":"0e2f9d6f-edc8-416e-b9af-b0e2d92e15ad","hoverSelected":false,"hover_selected":false,"drag_selected":false,"selected":false},{"active":true,"name":"square-brick-02.png","description":"__","gravity":"medium","__initializers":[],"img":{},"src":"http://localhost:3137/assets/uploads/square-brick-02.png","__mapScale":false,"__mapSize":{"x":200,"y":200,"z":0},"frameSize":{"x":200,"y":200,"z":0},"type":"basic","animations":[{"defaultArgs":{"name":"my-animation","description":"my-description","frames":[],"type":"none","delay":0,"frameSize":{"x":44,"y":44,"z":0},"frameBounds":{"min":{"x":0,"y":0,"z":0},"max":{"x":0,"y":0,"z":0},"termPoint":{"x":0,"y":0,"z":0}},"frameOffset":{"x":0,"y":0,"z":0},"flipX":false,"duration":1000,"size":{"x":20,"y":20,"z":20}},"name":"my-animation","description":"my-description","image":{"image":{},"src":"http://localhost:3137/assets/uploads/square-brick-02.png","domElement":{}},"src":"http://localhost:3137/assets/uploads/square-brick-02.png","domElement":{},"frameSize":{"x":200,"y":200,"z":0},"frameBounds":{"min":{"x":0,"y":0,"z":0},"max":{"x":0,"y":0,"z":0},"termPoint":{"x":0,"y":0,"z":0}},"frameOffset":{"x":0,"y":0,"z":0},"extras":false,"frames":[{"image":{"image":{},"src":"http://localhost:3137/assets/uploads/square-brick-02.png","domElement":{}},"frameSize":{"x":200,"y":200,"z":0},"framePos":{"x":0,"y":0}}],"flipX":false,"cix":0,"selected_frame":{"image":{"image":{},"src":"http://localhost:3137/assets/uploads/square-brick-02.png","domElement":{}},"frameSize":{"x":200,"y":200,"z":0},"framePos":{"x":0,"y":0}},"timer":0,"duration":1000,"seesaw_mode":false}],"motions":[],"projectiles":[],"sounds":[],"image":{"image":{},"src":"http://localhost:3137/assets/uploads/square-brick-02.png","domElement":{}},"size":{"x":200,"y":200,"z":0},"position":{"x":1200,"y":4750,"z":0},"collision_bounds":{"min":{"x":0,"y":0,"z":0},"max":{"x":0,"y":0,"z":0}},"rotation":{"x":0,"y":0,"z":0},"selected_animation":{"defaultArgs":{"name":"my-animation","description":"my-description","frames":[],"type":"none","delay":0,"frameSize":{"x":44,"y":44,"z":0},"frameBounds":{"min":{"x":0,"y":0,"z":0},"max":{"x":0,"y":0,"z":0},"termPoint":{"x":0,"y":0,"z":0}},"frameOffset":{"x":0,"y":0,"z":0},"flipX":false,"duration":1000,"size":{"x":20,"y":20,"z":20}},"name":"my-animation","description":"my-description","image":{"image":{},"src":"http://localhost:3137/assets/uploads/square-brick-02.png","domElement":{}},"src":"http://localhost:3137/assets/uploads/square-brick-02.png","domElement":{},"frameSize":{"x":200,"y":200,"z":0},"frameBounds":{"min":{"x":0,"y":0,"z":0},"max":{"x":0,"y":0,"z":0},"termPoint":{"x":0,"y":0,"z":0}},"frameOffset":{"x":0,"y":0,"z":0},"extras":false,"frames":[{"image":{"image":{},"src":"http://localhost:3137/assets/uploads/square-brick-02.png","domElement":{}},"frameSize":{"x":200,"y":200,"z":0},"framePos":{"x":0,"y":0}}],"flipX":false,"cix":0,"selected_frame":{"image":{"image":{},"src":"http://localhost:3137/assets/uploads/square-brick-02.png","domElement":{}},"frameSize":{"x":200,"y":200,"z":0},"framePos":{"x":0,"y":0}},"timer":0,"duration":1000,"seesaw_mode":false},"speed":{"x":0,"y":0,"z":0},"acceleration":{"x":0,"y":0,"z":0},"rot_speed":{"x":0,"y":0,"z":0},"rot_accel":{"x":0,"y":0,"z":0},"padding":{"x":0,"y":0,"z":0},"tag":"square-brick-02.png","mapSize":{"x":200,"y":200,"z":0},"id":"77991b4e-2d7f-45b3-8a7e-f554a50405e4","hoverSelected":false,"hover_selected":false,"drag_selected":false,"selected":false},{"active":true,"name":"square-brick-02.png","description":"__","gravity":"medium","__initializers":[],"img":{},"src":"http://localhost:3137/assets/uploads/square-brick-02.png","__mapScale":false,"__mapSize":{"x":200,"y":200,"z":0},"frameSize":{"x":200,"y":200,"z":0},"type":"basic","animations":[{"defaultArgs":{"name":"my-animation","description":"my-description","frames":[],"type":"none","delay":0,"frameSize":{"x":44,"y":44,"z":0},"frameBounds":{"min":{"x":0,"y":0,"z":0},"max":{"x":0,"y":0,"z":0},"termPoint":{"x":0,"y":0,"z":0}},"frameOffset":{"x":0,"y":0,"z":0},"flipX":false,"duration":1000,"size":{"x":20,"y":20,"z":20}},"name":"my-animation","description":"my-description","image":{"image":{},"src":"http://localhost:3137/assets/uploads/square-brick-02.png","domElement":{}},"src":"http://localhost:3137/assets/uploads/square-brick-02.png","domElement":{},"frameSize":{"x":200,"y":200,"z":0},"frameBounds":{"min":{"x":0,"y":0,"z":0},"max":{"x":0,"y":0,"z":0},"termPoint":{"x":0,"y":0,"z":0}},"frameOffset":{"x":0,"y":0,"z":0},"extras":false,"frames":[{"image":{"image":{},"src":"http://localhost:3137/assets/uploads/square-brick-02.png","domElement":{}},"frameSize":{"x":200,"y":200,"z":0},"framePos":{"x":0,"y":0}}],"flipX":false,"cix":0,"selected_frame":{"image":{"image":{},"src":"http://localhost:3137/assets/uploads/square-brick-02.png","domElement":{}},"frameSize":{"x":200,"y":200,"z":0},"framePos":{"x":0,"y":0}},"timer":0,"duration":1000,"seesaw_mode":false}],"motions":[],"projectiles":[],"sounds":[],"image":{"image":{},"src":"http://localhost:3137/assets/uploads/square-brick-02.png","domElement":{}},"size":{"x":200,"y":200,"z":0},"position":{"x":1400,"y":4750,"z":0},"collision_bounds":{"min":{"x":0,"y":0,"z":0},"max":{"x":0,"y":0,"z":0}},"rotation":{"x":0,"y":0,"z":0},"selected_animation":{"defaultArgs":{"name":"my-animation","description":"my-description","frames":[],"type":"none","delay":0,"frameSize":{"x":44,"y":44,"z":0},"frameBounds":{"min":{"x":0,"y":0,"z":0},"max":{"x":0,"y":0,"z":0},"termPoint":{"x":0,"y":0,"z":0}},"frameOffset":{"x":0,"y":0,"z":0},"flipX":false,"duration":1000,"size":{"x":20,"y":20,"z":20}},"name":"my-animation","description":"my-description","image":{"image":{},"src":"http://localhost:3137/assets/uploads/square-brick-02.png","domElement":{}},"src":"http://localhost:3137/assets/uploads/square-brick-02.png","domElement":{},"frameSize":{"x":200,"y":200,"z":0},"frameBounds":{"min":{"x":0,"y":0,"z":0},"max":{"x":0,"y":0,"z":0},"termPoint":{"x":0,"y":0,"z":0}},"frameOffset":{"x":0,"y":0,"z":0},"extras":false,"frames":[{"image":{"image":{},"src":"http://localhost:3137/assets/uploads/square-brick-02.png","domElement":{}},"frameSize":{"x":200,"y":200,"z":0},"framePos":{"x":0,"y":0}}],"flipX":false,"cix":0,"selected_frame":{"image":{"image":{},"src":"http://localhost:3137/assets/uploads/square-brick-02.png","domElement":{}},"frameSize":{"x":200,"y":200,"z":0},"framePos":{"x":0,"y":0}},"timer":0,"duration":1000,"seesaw_mode":false},"speed":{"x":0,"y":0,"z":0},"acceleration":{"x":0,"y":0,"z":0},"rot_speed":{"x":0,"y":0,"z":0},"rot_accel":{"x":0,"y":0,"z":0},"padding":{"x":0,"y":0,"z":0},"tag":"square-brick-02.png","mapSize":{"x":200,"y":200,"z":0},"id":"afcf9b61-61f0-4de4-9fa4-b8cb338a728d","hoverSelected":false,"hover_selected":false,"drag_selected":false,"selected":false},{"active":true,"name":"square-brick-02.png","description":"__","gravity":"medium","__initializers":[],"img":{},"src":"http://localhost:3137/assets/uploads/square-brick-02.png","__mapScale":false,"__mapSize":{"x":200,"y":200,"z":0},"frameSize":{"x":200,"y":200,"z":0},"type":"basic","animations":[{"defaultArgs":{"name":"my-animation","description":"my-description","frames":[],"type":"none","delay":0,"frameSize":{"x":44,"y":44,"z":0},"frameBounds":{"min":{"x":0,"y":0,"z":0},"max":{"x":0,"y":0,"z":0},"termPoint":{"x":0,"y":0,"z":0}},"frameOffset":{"x":0,"y":0,"z":0},"flipX":false,"duration":1000,"size":{"x":20,"y":20,"z":20}},"name":"my-animation","description":"my-description","image":{"image":{},"src":"http://localhost:3137/assets/uploads/square-brick-02.png","domElement":{}},"src":"http://localhost:3137/assets/uploads/square-brick-02.png","domElement":{},"frameSize":{"x":200,"y":200,"z":0},"frameBounds":{"min":{"x":0,"y":0,"z":0},"max":{"x":0,"y":0,"z":0},"termPoint":{"x":0,"y":0,"z":0}},"frameOffset":{"x":0,"y":0,"z":0},"extras":false,"frames":[{"image":{"image":{},"src":"http://localhost:3137/assets/uploads/square-brick-02.png","domElement":{}},"frameSize":{"x":200,"y":200,"z":0},"framePos":{"x":0,"y":0}}],"flipX":false,"cix":0,"selected_frame":{"image":{"image":{},"src":"http://localhost:3137/assets/uploads/square-brick-02.png","domElement":{}},"frameSize":{"x":200,"y":200,"z":0},"framePos":{"x":0,"y":0}},"timer":0,"duration":1000,"seesaw_mode":false}],"motions":[],"projectiles":[],"sounds":[],"image":{"image":{},"src":"http://localhost:3137/assets/uploads/square-brick-02.png","domElement":{}},"size":{"x":200,"y":200,"z":0},"position":{"x":1600,"y":4750,"z":0},"collision_bounds":{"min":{"x":0,"y":0,"z":0},"max":{"x":0,"y":0,"z":0}},"rotation":{"x":0,"y":0,"z":0},"selected_animation":{"defaultArgs":{"name":"my-animation","description":"my-description","frames":[],"type":"none","delay":0,"frameSize":{"x":44,"y":44,"z":0},"frameBounds":{"min":{"x":0,"y":0,"z":0},"max":{"x":0,"y":0,"z":0},"termPoint":{"x":0,"y":0,"z":0}},"frameOffset":{"x":0,"y":0,"z":0},"flipX":false,"duration":1000,"size":{"x":20,"y":20,"z":20}},"name":"my-animation","description":"my-description","image":{"image":{},"src":"http://localhost:3137/assets/uploads/square-brick-02.png","domElement":{}},"src":"http://localhost:3137/assets/uploads/square-brick-02.png","domElement":{},"frameSize":{"x":200,"y":200,"z":0},"frameBounds":{"min":{"x":0,"y":0,"z":0},"max":{"x":0,"y":0,"z":0},"termPoint":{"x":0,"y":0,"z":0}},"frameOffset":{"x":0,"y":0,"z":0},"extras":false,"frames":[{"image":{"image":{},"src":"http://localhost:3137/assets/uploads/square-brick-02.png","domElement":{}},"frameSize":{"x":200,"y":200,"z":0},"framePos":{"x":0,"y":0}}],"flipX":false,"cix":0,"selected_frame":{"image":{"image":{},"src":"http://localhost:3137/assets/uploads/square-brick-02.png","domElement":{}},"frameSize":{"x":200,"y":200,"z":0},"framePos":{"x":0,"y":0}},"timer":0,"duration":1000,"seesaw_mode":false},"speed":{"x":0,"y":0,"z":0},"acceleration":{"x":0,"y":0,"z":0},"rot_speed":{"x":0,"y":0,"z":0},"rot_accel":{"x":0,"y":0,"z":0},"padding":{"x":0,"y":0,"z":0},"tag":"square-brick-02.png","mapSize":{"x":200,"y":200,"z":0},"id":"f63399b4-c0b0-4206-9798-6e2231908778","hoverSelected":false,"hover_selected":false,"drag_selected":false,"selected":false},{"active":true,"name":"square-brick-02.png","description":"__","gravity":"medium","__initializers":[],"img":{},"src":"http://localhost:3137/assets/uploads/square-brick-02.png","__mapScale":false,"__mapSize":{"x":200,"y":200,"z":0},"frameSize":{"x":200,"y":200,"z":0},"type":"basic","animations":[{"defaultArgs":{"name":"my-animation","description":"my-description","frames":[],"type":"none","delay":0,"frameSize":{"x":44,"y":44,"z":0},"frameBounds":{"min":{"x":0,"y":0,"z":0},"max":{"x":0,"y":0,"z":0},"termPoint":{"x":0,"y":0,"z":0}},"frameOffset":{"x":0,"y":0,"z":0},"flipX":false,"duration":1000,"size":{"x":20,"y":20,"z":20}},"name":"my-animation","description":"my-description","image":{"image":{},"src":"http://localhost:3137/assets/uploads/square-brick-02.png","domElement":{}},"src":"http://localhost:3137/assets/uploads/square-brick-02.png","domElement":{},"frameSize":{"x":200,"y":200,"z":0},"frameBounds":{"min":{"x":0,"y":0,"z":0},"max":{"x":0,"y":0,"z":0},"termPoint":{"x":0,"y":0,"z":0}},"frameOffset":{"x":0,"y":0,"z":0},"extras":false,"frames":[{"image":{"image":{},"src":"http://localhost:3137/assets/uploads/square-brick-02.png","domElement":{}},"frameSize":{"x":200,"y":200,"z":0},"framePos":{"x":0,"y":0}}],"flipX":false,"cix":0,"selected_frame":{"image":{"image":{},"src":"http://localhost:3137/assets/uploads/square-brick-02.png","domElement":{}},"frameSize":{"x":200,"y":200,"z":0},"framePos":{"x":0,"y":0}},"timer":0,"duration":1000,"seesaw_mode":false}],"motions":[],"projectiles":[],"sounds":[],"image":{"image":{},"src":"http://localhost:3137/assets/uploads/square-brick-02.png","domElement":{}},"size":{"x":200,"y":200,"z":0},"position":{"x":1800,"y":4750,"z":0},"collision_bounds":{"min":{"x":0,"y":0,"z":0},"max":{"x":0,"y":0,"z":0}},"rotation":{"x":0,"y":0,"z":0},"selected_animation":{"defaultArgs":{"name":"my-animation","description":"my-description","frames":[],"type":"none","delay":0,"frameSize":{"x":44,"y":44,"z":0},"frameBounds":{"min":{"x":0,"y":0,"z":0},"max":{"x":0,"y":0,"z":0},"termPoint":{"x":0,"y":0,"z":0}},"frameOffset":{"x":0,"y":0,"z":0},"flipX":false,"duration":1000,"size":{"x":20,"y":20,"z":20}},"name":"my-animation","description":"my-description","image":{"image":{},"src":"http://localhost:3137/assets/uploads/square-brick-02.png","domElement":{}},"src":"http://localhost:3137/assets/uploads/square-brick-02.png","domElement":{},"frameSize":{"x":200,"y":200,"z":0},"frameBounds":{"min":{"x":0,"y":0,"z":0},"max":{"x":0,"y":0,"z":0},"termPoint":{"x":0,"y":0,"z":0}},"frameOffset":{"x":0,"y":0,"z":0},"extras":false,"frames":[{"image":{"image":{},"src":"http://localhost:3137/assets/uploads/square-brick-02.png","domElement":{}},"frameSize":{"x":200,"y":200,"z":0},"framePos":{"x":0,"y":0}}],"flipX":false,"cix":0,"selected_frame":{"image":{"image":{},"src":"http://localhost:3137/assets/uploads/square-brick-02.png","domElement":{}},"frameSize":{"x":200,"y":200,"z":0},"framePos":{"x":0,"y":0}},"timer":0,"duration":1000,"seesaw_mode":false},"speed":{"x":0,"y":0,"z":0},"acceleration":{"x":0,"y":0,"z":0},"rot_speed":{"x":0,"y":0,"z":0},"rot_accel":{"x":0,"y":0,"z":0},"padding":{"x":0,"y":0,"z":0},"tag":"square-brick-02.png","mapSize":{"x":200,"y":200,"z":0},"id":"7126fbb9-8a3d-40ac-b37c-ac7ac3a41882","hoverSelected":false,"hover_selected":false,"drag_selected":false,"selected":false},{"active":true,"name":"square-brick-02.png","description":"__","gravity":"medium","__initializers":[],"img":{},"src":"http://localhost:3137/assets/uploads/square-brick-02.png","__mapScale":false,"__mapSize":{"x":200,"y":200,"z":0},"frameSize":{"x":200,"y":200,"z":0},"type":"basic","animations":[{"defaultArgs":{"name":"my-animation","description":"my-description","frames":[],"type":"none","delay":0,"frameSize":{"x":44,"y":44,"z":0},"frameBounds":{"min":{"x":0,"y":0,"z":0},"max":{"x":0,"y":0,"z":0},"termPoint":{"x":0,"y":0,"z":0}},"frameOffset":{"x":0,"y":0,"z":0},"flipX":false,"duration":1000,"size":{"x":20,"y":20,"z":20}},"name":"my-animation","description":"my-description","image":{"image":{},"src":"http://localhost:3137/assets/uploads/square-brick-02.png","domElement":{}},"src":"http://localhost:3137/assets/uploads/square-brick-02.png","domElement":{},"frameSize":{"x":200,"y":200,"z":0},"frameBounds":{"min":{"x":0,"y":0,"z":0},"max":{"x":0,"y":0,"z":0},"termPoint":{"x":0,"y":0,"z":0}},"frameOffset":{"x":0,"y":0,"z":0},"extras":false,"frames":[{"image":{"image":{},"src":"http://localhost:3137/assets/uploads/square-brick-02.png","domElement":{}},"frameSize":{"x":200,"y":200,"z":0},"framePos":{"x":0,"y":0}}],"flipX":false,"cix":0,"selected_frame":{"image":{"image":{},"src":"http://localhost:3137/assets/uploads/square-brick-02.png","domElement":{}},"frameSize":{"x":200,"y":200,"z":0},"framePos":{"x":0,"y":0}},"timer":0,"duration":1000,"seesaw_mode":false}],"motions":[],"projectiles":[],"sounds":[],"image":{"image":{},"src":"http://localhost:3137/assets/uploads/square-brick-02.png","domElement":{}},"size":{"x":200,"y":200,"z":0},"position":{"x":1800,"y":4550,"z":0},"collision_bounds":{"min":{"x":0,"y":0,"z":0},"max":{"x":0,"y":0,"z":0}},"rotation":{"x":0,"y":0,"z":0},"selected_animation":{"defaultArgs":{"name":"my-animation","description":"my-description","frames":[],"type":"none","delay":0,"frameSize":{"x":44,"y":44,"z":0},"frameBounds":{"min":{"x":0,"y":0,"z":0},"max":{"x":0,"y":0,"z":0},"termPoint":{"x":0,"y":0,"z":0}},"frameOffset":{"x":0,"y":0,"z":0},"flipX":false,"duration":1000,"size":{"x":20,"y":20,"z":20}},"name":"my-animation","description":"my-description","image":{"image":{},"src":"http://localhost:3137/assets/uploads/square-brick-02.png","domElement":{}},"src":"http://localhost:3137/assets/uploads/square-brick-02.png","domElement":{},"frameSize":{"x":200,"y":200,"z":0},"frameBounds":{"min":{"x":0,"y":0,"z":0},"max":{"x":0,"y":0,"z":0},"termPoint":{"x":0,"y":0,"z":0}},"frameOffset":{"x":0,"y":0,"z":0},"extras":false,"frames":[{"image":{"image":{},"src":"http://localhost:3137/assets/uploads/square-brick-02.png","domElement":{}},"frameSize":{"x":200,"y":200,"z":0},"framePos":{"x":0,"y":0}}],"flipX":false,"cix":0,"selected_frame":{"image":{"image":{},"src":"http://localhost:3137/assets/uploads/square-brick-02.png","domElement":{}},"frameSize":{"x":200,"y":200,"z":0},"framePos":{"x":0,"y":0}},"timer":0,"duration":1000,"seesaw_mode":false},"speed":{"x":0,"y":0,"z":0},"acceleration":{"x":0,"y":0,"z":0},"rot_speed":{"x":0,"y":0,"z":0},"rot_accel":{"x":0,"y":0,"z":0},"padding":{"x":0,"y":0,"z":0},"tag":"square-brick-02.png","mapSize":{"x":200,"y":200,"z":0},"id":"91cadc58-40cb-4aa1-8b44-99b077b82beb","hoverSelected":false,"hover_selected":false,"drag_selected":false,"selected":false},{"active":true,"name":"square-brick-02.png","description":"__","gravity":"medium","__initializers":[],"img":{},"src":"http://localhost:3137/assets/uploads/square-brick-02.png","__mapScale":false,"__mapSize":{"x":200,"y":200,"z":0},"frameSize":{"x":200,"y":200,"z":0},"type":"basic","animations":[{"defaultArgs":{"name":"my-animation","description":"my-description","frames":[],"type":"none","delay":0,"frameSize":{"x":44,"y":44,"z":0},"frameBounds":{"min":{"x":0,"y":0,"z":0},"max":{"x":0,"y":0,"z":0},"termPoint":{"x":0,"y":0,"z":0}},"frameOffset":{"x":0,"y":0,"z":0},"flipX":false,"duration":1000,"size":{"x":20,"y":20,"z":20}},"name":"my-animation","description":"my-description","image":{"image":{},"src":"http://localhost:3137/assets/uploads/square-brick-02.png","domElement":{}},"src":"http://localhost:3137/assets/uploads/square-brick-02.png","domElement":{},"frameSize":{"x":200,"y":200,"z":0},"frameBounds":{"min":{"x":0,"y":0,"z":0},"max":{"x":0,"y":0,"z":0},"termPoint":{"x":0,"y":0,"z":0}},"frameOffset":{"x":0,"y":0,"z":0},"extras":false,"frames":[{"image":{"image":{},"src":"http://localhost:3137/assets/uploads/square-brick-02.png","domElement":{}},"frameSize":{"x":200,"y":200,"z":0},"framePos":{"x":0,"y":0}}],"flipX":false,"cix":0,"selected_frame":{"image":{"image":{},"src":"http://localhost:3137/assets/uploads/square-brick-02.png","domElement":{}},"frameSize":{"x":200,"y":200,"z":0},"framePos":{"x":0,"y":0}},"timer":0,"duration":1000,"seesaw_mode":false}],"motions":[],"projectiles":[],"sounds":[],"image":{"image":{},"src":"http://localhost:3137/assets/uploads/square-brick-02.png","domElement":{}},"size":{"x":200,"y":200,"z":0},"position":{"x":1800,"y":4350,"z":0},"collision_bounds":{"min":{"x":0,"y":0,"z":0},"max":{"x":0,"y":0,"z":0}},"rotation":{"x":0,"y":0,"z":0},"selected_animation":{"defaultArgs":{"name":"my-animation","description":"my-description","frames":[],"type":"none","delay":0,"frameSize":{"x":44,"y":44,"z":0},"frameBounds":{"min":{"x":0,"y":0,"z":0},"max":{"x":0,"y":0,"z":0},"termPoint":{"x":0,"y":0,"z":0}},"frameOffset":{"x":0,"y":0,"z":0},"flipX":false,"duration":1000,"size":{"x":20,"y":20,"z":20}},"name":"my-animation","description":"my-description","image":{"image":{},"src":"http://localhost:3137/assets/uploads/square-brick-02.png","domElement":{}},"src":"http://localhost:3137/assets/uploads/square-brick-02.png","domElement":{},"frameSize":{"x":200,"y":200,"z":0},"frameBounds":{"min":{"x":0,"y":0,"z":0},"max":{"x":0,"y":0,"z":0},"termPoint":{"x":0,"y":0,"z":0}},"frameOffset":{"x":0,"y":0,"z":0},"extras":false,"frames":[{"image":{"image":{},"src":"http://localhost:3137/assets/uploads/square-brick-02.png","domElement":{}},"frameSize":{"x":200,"y":200,"z":0},"framePos":{"x":0,"y":0}}],"flipX":false,"cix":0,"selected_frame":{"image":{"image":{},"src":"http://localhost:3137/assets/uploads/square-brick-02.png","domElement":{}},"frameSize":{"x":200,"y":200,"z":0},"framePos":{"x":0,"y":0}},"timer":0,"duration":1000,"seesaw_mode":false},"speed":{"x":0,"y":0,"z":0},"acceleration":{"x":0,"y":0,"z":0},"rot_speed":{"x":0,"y":0,"z":0},"rot_accel":{"x":0,"y":0,"z":0},"padding":{"x":0,"y":0,"z":0},"tag":"square-brick-02.png","mapSize":{"x":200,"y":200,"z":0},"id":"cd91b39e-a815-43a4-a1e5-8281da6a0d3d","hoverSelected":false,"hover_selected":false,"drag_selected":false,"selected":false},{"active":true,"name":"square-brick-02.png","description":"__","gravity":"medium","__initializers":[],"img":{},"src":"http://localhost:3137/assets/uploads/square-brick-02.png","__mapScale":false,"__mapSize":{"x":200,"y":200,"z":0},"frameSize":{"x":200,"y":200,"z":0},"type":"basic","animations":[{"defaultArgs":{"name":"my-animation","description":"my-description","frames":[],"type":"none","delay":0,"frameSize":{"x":44,"y":44,"z":0},"frameBounds":{"min":{"x":0,"y":0,"z":0},"max":{"x":0,"y":0,"z":0},"termPoint":{"x":0,"y":0,"z":0}},"frameOffset":{"x":0,"y":0,"z":0},"flipX":false,"duration":1000,"size":{"x":20,"y":20,"z":20}},"name":"my-animation","description":"my-description","image":{"image":{},"src":"http://localhost:3137/assets/uploads/square-brick-02.png","domElement":{}},"src":"http://localhost:3137/assets/uploads/square-brick-02.png","domElement":{},"frameSize":{"x":200,"y":200,"z":0},"frameBounds":{"min":{"x":0,"y":0,"z":0},"max":{"x":0,"y":0,"z":0},"termPoint":{"x":0,"y":0,"z":0}},"frameOffset":{"x":0,"y":0,"z":0},"extras":false,"frames":[{"image":{"image":{},"src":"http://localhost:3137/assets/uploads/square-brick-02.png","domElement":{}},"frameSize":{"x":200,"y":200,"z":0},"framePos":{"x":0,"y":0}}],"flipX":false,"cix":0,"selected_frame":{"image":{"image":{},"src":"http://localhost:3137/assets/uploads/square-brick-02.png","domElement":{}},"frameSize":{"x":200,"y":200,"z":0},"framePos":{"x":0,"y":0}},"timer":0,"duration":1000,"seesaw_mode":false}],"motions":[],"projectiles":[],"sounds":[],"image":{"image":{},"src":"http://localhost:3137/assets/uploads/square-brick-02.png","domElement":{}},"size":{"x":200,"y":200,"z":0},"position":{"x":2000,"y":4350,"z":0},"collision_bounds":{"min":{"x":0,"y":0,"z":0},"max":{"x":0,"y":0,"z":0}},"rotation":{"x":0,"y":0,"z":0},"selected_animation":{"defaultArgs":{"name":"my-animation","description":"my-description","frames":[],"type":"none","delay":0,"frameSize":{"x":44,"y":44,"z":0},"frameBounds":{"min":{"x":0,"y":0,"z":0},"max":{"x":0,"y":0,"z":0},"termPoint":{"x":0,"y":0,"z":0}},"frameOffset":{"x":0,"y":0,"z":0},"flipX":false,"duration":1000,"size":{"x":20,"y":20,"z":20}},"name":"my-animation","description":"my-description","image":{"image":{},"src":"http://localhost:3137/assets/uploads/square-brick-02.png","domElement":{}},"src":"http://localhost:3137/assets/uploads/square-brick-02.png","domElement":{},"frameSize":{"x":200,"y":200,"z":0},"frameBounds":{"min":{"x":0,"y":0,"z":0},"max":{"x":0,"y":0,"z":0},"termPoint":{"x":0,"y":0,"z":0}},"frameOffset":{"x":0,"y":0,"z":0},"extras":false,"frames":[{"image":{"image":{},"src":"http://localhost:3137/assets/uploads/square-brick-02.png","domElement":{}},"frameSize":{"x":200,"y":200,"z":0},"framePos":{"x":0,"y":0}}],"flipX":false,"cix":0,"selected_frame":{"image":{"image":{},"src":"http://localhost:3137/assets/uploads/square-brick-02.png","domElement":{}},"frameSize":{"x":200,"y":200,"z":0},"framePos":{"x":0,"y":0}},"timer":0,"duration":1000,"seesaw_mode":false},"speed":{"x":0,"y":0,"z":0},"acceleration":{"x":0,"y":0,"z":0},"rot_speed":{"x":0,"y":0,"z":0},"rot_accel":{"x":0,"y":0,"z":0},"padding":{"x":0,"y":0,"z":0},"tag":"square-brick-02.png","mapSize":{"x":200,"y":200,"z":0},"id":"c1d1cb3d-e675-4740-ac39-738ff463ff30","hoverSelected":false,"hover_selected":false,"drag_selected":false,"selected":false},{"active":true,"name":"square-brick-02.png","description":"__","gravity":"medium","__initializers":[],"img":{},"src":"http://localhost:3137/assets/uploads/square-brick-02.png","__mapScale":false,"__mapSize":{"x":200,"y":200,"z":0},"frameSize":{"x":200,"y":200,"z":0},"type":"basic","animations":[{"defaultArgs":{"name":"my-animation","description":"my-description","frames":[],"type":"none","delay":0,"frameSize":{"x":44,"y":44,"z":0},"frameBounds":{"min":{"x":0,"y":0,"z":0},"max":{"x":0,"y":0,"z":0},"termPoint":{"x":0,"y":0,"z":0}},"frameOffset":{"x":0,"y":0,"z":0},"flipX":false,"duration":1000,"size":{"x":20,"y":20,"z":20}},"name":"my-animation","description":"my-description","image":{"image":{},"src":"http://localhost:3137/assets/uploads/square-brick-02.png","domElement":{}},"src":"http://localhost:3137/assets/uploads/square-brick-02.png","domElement":{},"frameSize":{"x":200,"y":200,"z":0},"frameBounds":{"min":{"x":0,"y":0,"z":0},"max":{"x":0,"y":0,"z":0},"termPoint":{"x":0,"y":0,"z":0}},"frameOffset":{"x":0,"y":0,"z":0},"extras":false,"frames":[{"image":{"image":{},"src":"http://localhost:3137/assets/uploads/square-brick-02.png","domElement":{}},"frameSize":{"x":200,"y":200,"z":0},"framePos":{"x":0,"y":0}}],"flipX":false,"cix":0,"selected_frame":{"image":{"image":{},"src":"http://localhost:3137/assets/uploads/square-brick-02.png","domElement":{}},"frameSize":{"x":200,"y":200,"z":0},"framePos":{"x":0,"y":0}},"timer":0,"duration":1000,"seesaw_mode":false}],"motions":[],"projectiles":[],"sounds":[],"image":{"image":{},"src":"http://localhost:3137/assets/uploads/square-brick-02.png","domElement":{}},"size":{"x":200,"y":200,"z":0},"position":{"x":2200,"y":4350,"z":0},"collision_bounds":{"min":{"x":0,"y":0,"z":0},"max":{"x":0,"y":0,"z":0}},"rotation":{"x":0,"y":0,"z":0},"selected_animation":{"defaultArgs":{"name":"my-animation","description":"my-description","frames":[],"type":"none","delay":0,"frameSize":{"x":44,"y":44,"z":0},"frameBounds":{"min":{"x":0,"y":0,"z":0},"max":{"x":0,"y":0,"z":0},"termPoint":{"x":0,"y":0,"z":0}},"frameOffset":{"x":0,"y":0,"z":0},"flipX":false,"duration":1000,"size":{"x":20,"y":20,"z":20}},"name":"my-animation","description":"my-description","image":{"image":{},"src":"http://localhost:3137/assets/uploads/square-brick-02.png","domElement":{}},"src":"http://localhost:3137/assets/uploads/square-brick-02.png","domElement":{},"frameSize":{"x":200,"y":200,"z":0},"frameBounds":{"min":{"x":0,"y":0,"z":0},"max":{"x":0,"y":0,"z":0},"termPoint":{"x":0,"y":0,"z":0}},"frameOffset":{"x":0,"y":0,"z":0},"extras":false,"frames":[{"image":{"image":{},"src":"http://localhost:3137/assets/uploads/square-brick-02.png","domElement":{}},"frameSize":{"x":200,"y":200,"z":0},"framePos":{"x":0,"y":0}}],"flipX":false,"cix":0,"selected_frame":{"image":{"image":{},"src":"http://localhost:3137/assets/uploads/square-brick-02.png","domElement":{}},"frameSize":{"x":200,"y":200,"z":0},"framePos":{"x":0,"y":0}},"timer":0,"duration":1000,"seesaw_mode":false},"speed":{"x":0,"y":0,"z":0},"acceleration":{"x":0,"y":0,"z":0},"rot_speed":{"x":0,"y":0,"z":0},"rot_accel":{"x":0,"y":0,"z":0},"padding":{"x":0,"y":0,"z":0},"tag":"square-brick-02.png","mapSize":{"x":200,"y":200,"z":0},"id":"f397fd3e-d247-4e76-b2f9-c56a3cd126f4","hoverSelected":false,"hover_selected":false,"drag_selected":false,"selected":false},{"active":true,"name":"colored-brick-01-200x200.png","description":"__","gravity":"medium","__initializers":[],"img":{},"src":"http://localhost:3137/assets/uploads/colored-brick-01-200x200.png","__mapScale":false,"__mapSize":{"x":200,"y":200,"z":0},"frameSize":{"x":200,"y":200,"z":0},"type":"basic","animations":[{"defaultArgs":{"name":"my-animation","description":"my-description","frames":[],"type":"none","delay":0,"frameSize":{"x":44,"y":44,"z":0},"frameBounds":{"min":{"x":0,"y":0,"z":0},"max":{"x":0,"y":0,"z":0},"termPoint":{"x":0,"y":0,"z":0}},"frameOffset":{"x":0,"y":0,"z":0},"flipX":false,"duration":1000,"size":{"x":20,"y":20,"z":20}},"name":"my-animation","description":"my-description","image":{"image":{},"src":"http://localhost:3137/assets/uploads/colored-brick-01-200x200.png","domElement":{}},"src":"http://localhost:3137/assets/uploads/colored-brick-01-200x200.png","domElement":{},"frameSize":{"x":200,"y":200,"z":0},"frameBounds":{"min":{"x":0,"y":0,"z":0},"max":{"x":0,"y":0,"z":0},"termPoint":{"x":0,"y":0,"z":0}},"frameOffset":{"x":0,"y":0,"z":0},"extras":false,"frames":[{"image":{"image":{},"src":"http://localhost:3137/assets/uploads/colored-brick-01-200x200.png","domElement":{}},"frameSize":{"x":200,"y":200,"z":0},"framePos":{"x":0,"y":0}}],"flipX":false,"cix":0,"selected_frame":{"image":{"image":{},"src":"http://localhost:3137/assets/uploads/colored-brick-01-200x200.png","domElement":{}},"frameSize":{"x":200,"y":200,"z":0},"framePos":{"x":0,"y":0}},"timer":0,"duration":1000,"seesaw_mode":false}],"motions":[],"projectiles":[],"sounds":[],"image":{"image":{},"src":"http://localhost:3137/assets/uploads/colored-brick-01-200x200.png","domElement":{}},"size":{"x":200,"y":200,"z":0},"position":{"x":250,"y":4300,"z":0},"collision_bounds":{"min":{"x":0,"y":0,"z":0},"max":{"x":0,"y":0,"z":0}},"rotation":{"x":0,"y":0,"z":0},"selected_animation":{"defaultArgs":{"name":"my-animation","description":"my-description","frames":[],"type":"none","delay":0,"frameSize":{"x":44,"y":44,"z":0},"frameBounds":{"min":{"x":0,"y":0,"z":0},"max":{"x":0,"y":0,"z":0},"termPoint":{"x":0,"y":0,"z":0}},"frameOffset":{"x":0,"y":0,"z":0},"flipX":false,"duration":1000,"size":{"x":20,"y":20,"z":20}},"name":"my-animation","description":"my-description","image":{"image":{},"src":"http://localhost:3137/assets/uploads/colored-brick-01-200x200.png","domElement":{}},"src":"http://localhost:3137/assets/uploads/colored-brick-01-200x200.png","domElement":{},"frameSize":{"x":200,"y":200,"z":0},"frameBounds":{"min":{"x":0,"y":0,"z":0},"max":{"x":0,"y":0,"z":0},"termPoint":{"x":0,"y":0,"z":0}},"frameOffset":{"x":0,"y":0,"z":0},"extras":false,"frames":[{"image":{"image":{},"src":"http://localhost:3137/assets/uploads/colored-brick-01-200x200.png","domElement":{}},"frameSize":{"x":200,"y":200,"z":0},"framePos":{"x":0,"y":0}}],"flipX":false,"cix":0,"selected_frame":{"image":{"image":{},"src":"http://localhost:3137/assets/uploads/colored-brick-01-200x200.png","domElement":{}},"frameSize":{"x":200,"y":200,"z":0},"framePos":{"x":0,"y":0}},"timer":0,"duration":1000,"seesaw_mode":false},"speed":{"x":0,"y":0,"z":0},"acceleration":{"x":0,"y":0,"z":0},"rot_speed":{"x":0,"y":0,"z":0},"rot_accel":{"x":0,"y":0,"z":0},"padding":{"x":0,"y":0,"z":0},"tag":"colored-brick-01-200x200.png","mapSize":{"x":200,"y":200,"z":0},"id":"deeee21a-5961-40aa-91da-4a6595420e5a","hoverSelected":false,"hover_selected":false,"drag_selected":false,"selected":false},{"active":true,"name":"colored-brick-01-200x200.png","description":"__","gravity":"medium","__initializers":[],"img":{},"src":"http://localhost:3137/assets/uploads/colored-brick-01-200x200.png","__mapScale":false,"__mapSize":{"x":200,"y":200,"z":0},"frameSize":{"x":200,"y":200,"z":0},"type":"basic","animations":[{"defaultArgs":{"name":"my-animation","description":"my-description","frames":[],"type":"none","delay":0,"frameSize":{"x":44,"y":44,"z":0},"frameBounds":{"min":{"x":0,"y":0,"z":0},"max":{"x":0,"y":0,"z":0},"termPoint":{"x":0,"y":0,"z":0}},"frameOffset":{"x":0,"y":0,"z":0},"flipX":false,"duration":1000,"size":{"x":20,"y":20,"z":20}},"name":"my-animation","description":"my-description","image":{"image":{},"src":"http://localhost:3137/assets/uploads/colored-brick-01-200x200.png","domElement":{}},"src":"http://localhost:3137/assets/uploads/colored-brick-01-200x200.png","domElement":{},"frameSize":{"x":200,"y":200,"z":0},"frameBounds":{"min":{"x":0,"y":0,"z":0},"max":{"x":0,"y":0,"z":0},"termPoint":{"x":0,"y":0,"z":0}},"frameOffset":{"x":0,"y":0,"z":0},"extras":false,"frames":[{"image":{"image":{},"src":"http://localhost:3137/assets/uploads/colored-brick-01-200x200.png","domElement":{}},"frameSize":{"x":200,"y":200,"z":0},"framePos":{"x":0,"y":0}}],"flipX":false,"cix":0,"selected_frame":{"image":{"image":{},"src":"http://localhost:3137/assets/uploads/colored-brick-01-200x200.png","domElement":{}},"frameSize":{"x":200,"y":200,"z":0},"framePos":{"x":0,"y":0}},"timer":0,"duration":1000,"seesaw_mode":false}],"motions":[],"projectiles":[],"sounds":[],"image":{"image":{},"src":"http://localhost:3137/assets/uploads/colored-brick-01-200x200.png","domElement":{}},"size":{"x":200,"y":200,"z":0},"position":{"x":1200,"y":4300,"z":0},"collision_bounds":{"min":{"x":0,"y":0,"z":0},"max":{"x":0,"y":0,"z":0}},"rotation":{"x":0,"y":0,"z":0},"selected_animation":{"defaultArgs":{"name":"my-animation","description":"my-description","frames":[],"type":"none","delay":0,"frameSize":{"x":44,"y":44,"z":0},"frameBounds":{"min":{"x":0,"y":0,"z":0},"max":{"x":0,"y":0,"z":0},"termPoint":{"x":0,"y":0,"z":0}},"frameOffset":{"x":0,"y":0,"z":0},"flipX":false,"duration":1000,"size":{"x":20,"y":20,"z":20}},"name":"my-animation","description":"my-description","image":{"image":{},"src":"http://localhost:3137/assets/uploads/colored-brick-01-200x200.png","domElement":{}},"src":"http://localhost:3137/assets/uploads/colored-brick-01-200x200.png","domElement":{},"frameSize":{"x":200,"y":200,"z":0},"frameBounds":{"min":{"x":0,"y":0,"z":0},"max":{"x":0,"y":0,"z":0},"termPoint":{"x":0,"y":0,"z":0}},"frameOffset":{"x":0,"y":0,"z":0},"extras":false,"frames":[{"image":{"image":{},"src":"http://localhost:3137/assets/uploads/colored-brick-01-200x200.png","domElement":{}},"frameSize":{"x":200,"y":200,"z":0},"framePos":{"x":0,"y":0}}],"flipX":false,"cix":0,"selected_frame":{"image":{"image":{},"src":"http://localhost:3137/assets/uploads/colored-brick-01-200x200.png","domElement":{}},"frameSize":{"x":200,"y":200,"z":0},"framePos":{"x":0,"y":0}},"timer":0,"duration":1000,"seesaw_mode":false},"speed":{"x":0,"y":0,"z":0},"acceleration":{"x":0,"y":0,"z":0},"rot_speed":{"x":0,"y":0,"z":0},"rot_accel":{"x":0,"y":0,"z":0},"padding":{"x":0,"y":0,"z":0},"tag":"colored-brick-01-200x200.png","mapSize":{"x":200,"y":200,"z":0},"id":"9856bc41-7d93-49b9-8e4e-a0ba6c7a0839","hoverSelected":false,"hover_selected":false,"drag_selected":false,"selected":false},{"active":true,"name":"brick_block","description":"__","gravity":"medium","__initializers":[],"img":{},"src":"http://localhost:3137/assets/game/image/bricks/square_brick.png","__mapScale":false,"__mapSize":{"x":40,"y":40,"z":0},"frameSize":{"x":85,"y":85,"z":0},"type":"basic","animations":[{"defaultArgs":{"name":"my-animation","description":"my-description","frames":[],"type":"none","delay":0,"frameSize":{"x":44,"y":44,"z":0},"frameBounds":{"min":{"x":0,"y":0,"z":0},"max":{"x":0,"y":0,"z":0},"termPoint":{"x":0,"y":0,"z":0}},"frameOffset":{"x":0,"y":0,"z":0},"flipX":false,"duration":1000,"size":{"x":20,"y":20,"z":20}},"name":"my-animation","description":"my-description","image":{"image":{},"src":"http://localhost:3137/assets/game/image/bricks/square_brick.png","domElement":{}},"src":"http://localhost:3137/assets/game/image/bricks/square_brick.png","domElement":{},"frameSize":{"x":85,"y":85,"z":0},"frameBounds":{"min":{"x":0,"y":0,"z":0},"max":{"x":0,"y":0,"z":0},"termPoint":{"x":0,"y":0,"z":0}},"frameOffset":{"x":0,"y":0,"z":0},"extras":false,"frames":[{"image":{"image":{},"src":"http://localhost:3137/assets/game/image/bricks/square_brick.png","domElement":{}},"frameSize":{"x":85,"y":85,"z":0},"framePos":{"x":0,"y":0}}],"flipX":false,"cix":0,"selected_frame":{"image":{"image":{},"src":"http://localhost:3137/assets/game/image/bricks/square_brick.png","domElement":{}},"frameSize":{"x":85,"y":85,"z":0},"framePos":{"x":0,"y":0}},"timer":0,"duration":1000,"seesaw_mode":false}],"motions":[],"projectiles":[],"sounds":[],"image":{"image":{},"src":"http://localhost:3137/assets/game/image/bricks/square_brick.png","domElement":{}},"size":{"x":40,"y":40,"z":0},"position":{"x":530,"y":4380,"z":0},"collision_bounds":{"min":{"x":0,"y":0,"z":0},"max":{"x":0,"y":0,"z":0}},"rotation":{"x":0,"y":0,"z":0},"selected_animation":{"defaultArgs":{"name":"my-animation","description":"my-description","frames":[],"type":"none","delay":0,"frameSize":{"x":44,"y":44,"z":0},"frameBounds":{"min":{"x":0,"y":0,"z":0},"max":{"x":0,"y":0,"z":0},"termPoint":{"x":0,"y":0,"z":0}},"frameOffset":{"x":0,"y":0,"z":0},"flipX":false,"duration":1000,"size":{"x":20,"y":20,"z":20}},"name":"my-animation","description":"my-description","image":{"image":{},"src":"http://localhost:3137/assets/game/image/bricks/square_brick.png","domElement":{}},"src":"http://localhost:3137/assets/game/image/bricks/square_brick.png","domElement":{},"frameSize":{"x":85,"y":85,"z":0},"frameBounds":{"min":{"x":0,"y":0,"z":0},"max":{"x":0,"y":0,"z":0},"termPoint":{"x":0,"y":0,"z":0}},"frameOffset":{"x":0,"y":0,"z":0},"extras":false,"frames":[{"image":{"image":{},"src":"http://localhost:3137/assets/game/image/bricks/square_brick.png","domElement":{}},"frameSize":{"x":85,"y":85,"z":0},"framePos":{"x":0,"y":0}}],"flipX":false,"cix":0,"selected_frame":{"image":{"image":{},"src":"http://localhost:3137/assets/game/image/bricks/square_brick.png","domElement":{}},"frameSize":{"x":85,"y":85,"z":0},"framePos":{"x":0,"y":0}},"timer":0,"duration":1000,"seesaw_mode":false},"speed":{"x":0,"y":0,"z":0},"acceleration":{"x":0,"y":0,"z":0},"rot_speed":{"x":0,"y":0,"z":0},"rot_accel":{"x":0,"y":0,"z":0},"padding":{"x":0,"y":0,"z":0},"tag":"brick_block","id":"be1ef606-6402-44ce-96e2-235000b53b9b","hoverSelected":false,"hover_selected":false,"drag_selected":false,"selected":false},{"active":true,"name":"brick_block","description":"__","gravity":"medium","__initializers":[],"img":{},"src":"http://localhost:3137/assets/game/image/bricks/square_brick.png","__mapScale":false,"__mapSize":{"x":40,"y":40,"z":0},"frameSize":{"x":85,"y":85,"z":0},"type":"basic","animations":[{"defaultArgs":{"name":"my-animation","description":"my-description","frames":[],"type":"none","delay":0,"frameSize":{"x":44,"y":44,"z":0},"frameBounds":{"min":{"x":0,"y":0,"z":0},"max":{"x":0,"y":0,"z":0},"termPoint":{"x":0,"y":0,"z":0}},"frameOffset":{"x":0,"y":0,"z":0},"flipX":false,"duration":1000,"size":{"x":20,"y":20,"z":20}},"name":"my-animation","description":"my-description","image":{"image":{},"src":"http://localhost:3137/assets/game/image/bricks/square_brick.png","domElement":{}},"src":"http://localhost:3137/assets/game/image/bricks/square_brick.png","domElement":{},"frameSize":{"x":85,"y":85,"z":0},"frameBounds":{"min":{"x":0,"y":0,"z":0},"max":{"x":0,"y":0,"z":0},"termPoint":{"x":0,"y":0,"z":0}},"frameOffset":{"x":0,"y":0,"z":0},"extras":false,"frames":[{"image":{"image":{},"src":"http://localhost:3137/assets/game/image/bricks/square_brick.png","domElement":{}},"frameSize":{"x":85,"y":85,"z":0},"framePos":{"x":0,"y":0}}],"flipX":false,"cix":0,"selected_frame":{"image":{"image":{},"src":"http://localhost:3137/assets/game/image/bricks/square_brick.png","domElement":{}},"frameSize":{"x":85,"y":85,"z":0},"framePos":{"x":0,"y":0}},"timer":0,"duration":1000,"seesaw_mode":false}],"motions":[],"projectiles":[],"sounds":[],"image":{"image":{},"src":"http://localhost:3137/assets/game/image/bricks/square_brick.png","domElement":{}},"size":{"x":40,"y":40,"z":0},"position":{"x":630,"y":4380,"z":0},"collision_bounds":{"min":{"x":0,"y":0,"z":0},"max":{"x":0,"y":0,"z":0}},"rotation":{"x":0,"y":0,"z":0},"selected_animation":{"defaultArgs":{"name":"my-animation","description":"my-description","frames":[],"type":"none","delay":0,"frameSize":{"x":44,"y":44,"z":0},"frameBounds":{"min":{"x":0,"y":0,"z":0},"max":{"x":0,"y":0,"z":0},"termPoint":{"x":0,"y":0,"z":0}},"frameOffset":{"x":0,"y":0,"z":0},"flipX":false,"duration":1000,"size":{"x":20,"y":20,"z":20}},"name":"my-animation","description":"my-description","image":{"image":{},"src":"http://localhost:3137/assets/game/image/bricks/square_brick.png","domElement":{}},"src":"http://localhost:3137/assets/game/image/bricks/square_brick.png","domElement":{},"frameSize":{"x":85,"y":85,"z":0},"frameBounds":{"min":{"x":0,"y":0,"z":0},"max":{"x":0,"y":0,"z":0},"termPoint":{"x":0,"y":0,"z":0}},"frameOffset":{"x":0,"y":0,"z":0},"extras":false,"frames":[{"image":{"image":{},"src":"http://localhost:3137/assets/game/image/bricks/square_brick.png","domElement":{}},"frameSize":{"x":85,"y":85,"z":0},"framePos":{"x":0,"y":0}}],"flipX":false,"cix":0,"selected_frame":{"image":{"image":{},"src":"http://localhost:3137/assets/game/image/bricks/square_brick.png","domElement":{}},"frameSize":{"x":85,"y":85,"z":0},"framePos":{"x":0,"y":0}},"timer":0,"duration":1000,"seesaw_mode":false},"speed":{"x":0,"y":0,"z":0},"acceleration":{"x":0,"y":0,"z":0},"rot_speed":{"x":0,"y":0,"z":0},"rot_accel":{"x":0,"y":0,"z":0},"padding":{"x":0,"y":0,"z":0},"tag":"brick_block","id":"669aa962-fa1c-427f-b01a-301d5c3d5c3d","hoverSelected":false,"hover_selected":false,"drag_selected":false,"selected":false},{"active":true,"name":"brick_block","description":"__","gravity":"medium","__initializers":[],"img":{},"src":"http://localhost:3137/assets/game/image/bricks/square_brick.png","__mapScale":false,"__mapSize":{"x":40,"y":40,"z":0},"frameSize":{"x":85,"y":85,"z":0},"type":"basic","animations":[{"defaultArgs":{"name":"my-animation","description":"my-description","frames":[],"type":"none","delay":0,"frameSize":{"x":44,"y":44,"z":0},"frameBounds":{"min":{"x":0,"y":0,"z":0},"max":{"x":0,"y":0,"z":0},"termPoint":{"x":0,"y":0,"z":0}},"frameOffset":{"x":0,"y":0,"z":0},"flipX":false,"duration":1000,"size":{"x":20,"y":20,"z":20}},"name":"my-animation","description":"my-description","image":{"image":{},"src":"http://localhost:3137/assets/game/image/bricks/square_brick.png","domElement":{}},"src":"http://localhost:3137/assets/game/image/bricks/square_brick.png","domElement":{},"frameSize":{"x":85,"y":85,"z":0},"frameBounds":{"min":{"x":0,"y":0,"z":0},"max":{"x":0,"y":0,"z":0},"termPoint":{"x":0,"y":0,"z":0}},"frameOffset":{"x":0,"y":0,"z":0},"extras":false,"frames":[{"image":{"image":{},"src":"http://localhost:3137/assets/game/image/bricks/square_brick.png","domElement":{}},"frameSize":{"x":85,"y":85,"z":0},"framePos":{"x":0,"y":0}}],"flipX":false,"cix":0,"selected_frame":{"image":{"image":{},"src":"http://localhost:3137/assets/game/image/bricks/square_brick.png","domElement":{}},"frameSize":{"x":85,"y":85,"z":0},"framePos":{"x":0,"y":0}},"timer":0,"duration":1000,"seesaw_mode":false}],"motions":[],"projectiles":[],"sounds":[],"image":{"image":{},"src":"http://localhost:3137/assets/game/image/bricks/square_brick.png","domElement":{}},"size":{"x":40,"y":40,"z":0},"position":{"x":730,"y":4380,"z":0},"collision_bounds":{"min":{"x":0,"y":0,"z":0},"max":{"x":0,"y":0,"z":0}},"rotation":{"x":0,"y":0,"z":0},"selected_animation":{"defaultArgs":{"name":"my-animation","description":"my-description","frames":[],"type":"none","delay":0,"frameSize":{"x":44,"y":44,"z":0},"frameBounds":{"min":{"x":0,"y":0,"z":0},"max":{"x":0,"y":0,"z":0},"termPoint":{"x":0,"y":0,"z":0}},"frameOffset":{"x":0,"y":0,"z":0},"flipX":false,"duration":1000,"size":{"x":20,"y":20,"z":20}},"name":"my-animation","description":"my-description","image":{"image":{},"src":"http://localhost:3137/assets/game/image/bricks/square_brick.png","domElement":{}},"src":"http://localhost:3137/assets/game/image/bricks/square_brick.png","domElement":{},"frameSize":{"x":85,"y":85,"z":0},"frameBounds":{"min":{"x":0,"y":0,"z":0},"max":{"x":0,"y":0,"z":0},"termPoint":{"x":0,"y":0,"z":0}},"frameOffset":{"x":0,"y":0,"z":0},"extras":false,"frames":[{"image":{"image":{},"src":"http://localhost:3137/assets/game/image/bricks/square_brick.png","domElement":{}},"frameSize":{"x":85,"y":85,"z":0},"framePos":{"x":0,"y":0}}],"flipX":false,"cix":0,"selected_frame":{"image":{"image":{},"src":"http://localhost:3137/assets/game/image/bricks/square_brick.png","domElement":{}},"frameSize":{"x":85,"y":85,"z":0},"framePos":{"x":0,"y":0}},"timer":0,"duration":1000,"seesaw_mode":false},"speed":{"x":0,"y":0,"z":0},"acceleration":{"x":0,"y":0,"z":0},"rot_speed":{"x":0,"y":0,"z":0},"rot_accel":{"x":0,"y":0,"z":0},"padding":{"x":0,"y":0,"z":0},"tag":"brick_block","id":"484ba747-55ad-4207-8007-e3c67f6d8484","hoverSelected":false,"hover_selected":false,"drag_selected":false,"selected":false},{"active":true,"name":"brick_block","description":"__","gravity":"medium","__initializers":[],"img":{},"src":"http://localhost:3137/assets/game/image/bricks/square_brick.png","__mapScale":false,"__mapSize":{"x":40,"y":40,"z":0},"frameSize":{"x":85,"y":85,"z":0},"type":"basic","animations":[{"defaultArgs":{"name":"my-animation","description":"my-description","frames":[],"type":"none","delay":0,"frameSize":{"x":44,"y":44,"z":0},"frameBounds":{"min":{"x":0,"y":0,"z":0},"max":{"x":0,"y":0,"z":0},"termPoint":{"x":0,"y":0,"z":0}},"frameOffset":{"x":0,"y":0,"z":0},"flipX":false,"duration":1000,"size":{"x":20,"y":20,"z":20}},"name":"my-animation","description":"my-description","image":{"image":{},"src":"http://localhost:3137/assets/game/image/bricks/square_brick.png","domElement":{}},"src":"http://localhost:3137/assets/game/image/bricks/square_brick.png","domElement":{},"frameSize":{"x":85,"y":85,"z":0},"frameBounds":{"min":{"x":0,"y":0,"z":0},"max":{"x":0,"y":0,"z":0},"termPoint":{"x":0,"y":0,"z":0}},"frameOffset":{"x":0,"y":0,"z":0},"extras":false,"frames":[{"image":{"image":{},"src":"http://localhost:3137/assets/game/image/bricks/square_brick.png","domElement":{}},"frameSize":{"x":85,"y":85,"z":0},"framePos":{"x":0,"y":0}}],"flipX":false,"cix":0,"selected_frame":{"image":{"image":{},"src":"http://localhost:3137/assets/game/image/bricks/square_brick.png","domElement":{}},"frameSize":{"x":85,"y":85,"z":0},"framePos":{"x":0,"y":0}},"timer":0,"duration":1000,"seesaw_mode":false}],"motions":[],"projectiles":[],"sounds":[],"image":{"image":{},"src":"http://localhost:3137/assets/game/image/bricks/square_brick.png","domElement":{}},"size":{"x":40,"y":40,"z":0},"position":{"x":80,"y":4580,"z":0},"collision_bounds":{"min":{"x":0,"y":0,"z":0},"max":{"x":0,"y":0,"z":0}},"rotation":{"x":0,"y":0,"z":0},"selected_animation":{"defaultArgs":{"name":"my-animation","description":"my-description","frames":[],"type":"none","delay":0,"frameSize":{"x":44,"y":44,"z":0},"frameBounds":{"min":{"x":0,"y":0,"z":0},"max":{"x":0,"y":0,"z":0},"termPoint":{"x":0,"y":0,"z":0}},"frameOffset":{"x":0,"y":0,"z":0},"flipX":false,"duration":1000,"size":{"x":20,"y":20,"z":20}},"name":"my-animation","description":"my-description","image":{"image":{},"src":"http://localhost:3137/assets/game/image/bricks/square_brick.png","domElement":{}},"src":"http://localhost:3137/assets/game/image/bricks/square_brick.png","domElement":{},"frameSize":{"x":85,"y":85,"z":0},"frameBounds":{"min":{"x":0,"y":0,"z":0},"max":{"x":0,"y":0,"z":0},"termPoint":{"x":0,"y":0,"z":0}},"frameOffset":{"x":0,"y":0,"z":0},"extras":false,"frames":[{"image":{"image":{},"src":"http://localhost:3137/assets/game/image/bricks/square_brick.png","domElement":{}},"frameSize":{"x":85,"y":85,"z":0},"framePos":{"x":0,"y":0}}],"flipX":false,"cix":0,"selected_frame":{"image":{"image":{},"src":"http://localhost:3137/assets/game/image/bricks/square_brick.png","domElement":{}},"frameSize":{"x":85,"y":85,"z":0},"framePos":{"x":0,"y":0}},"timer":0,"duration":1000,"seesaw_mode":false},"speed":{"x":0,"y":0,"z":0},"acceleration":{"x":0,"y":0,"z":0},"rot_speed":{"x":0,"y":0,"z":0},"rot_accel":{"x":0,"y":0,"z":0},"padding":{"x":0,"y":0,"z":0},"tag":"brick_block","id":"2663053b-eeab-4451-91d7-1992eacb25c3","hoverSelected":false,"hover_selected":false,"drag_selected":false,"selected":false},{"active":true,"name":"brick_block","description":"__","gravity":"medium","__initializers":[],"img":{},"src":"http://localhost:3137/assets/game/image/bricks/square_brick.png","__mapScale":false,"__mapSize":{"x":40,"y":40,"z":0},"frameSize":{"x":85,"y":85,"z":0},"type":"basic","animations":[{"defaultArgs":{"name":"my-animation","description":"my-description","frames":[],"type":"none","delay":0,"frameSize":{"x":44,"y":44,"z":0},"frameBounds":{"min":{"x":0,"y":0,"z":0},"max":{"x":0,"y":0,"z":0},"termPoint":{"x":0,"y":0,"z":0}},"frameOffset":{"x":0,"y":0,"z":0},"flipX":false,"duration":1000,"size":{"x":20,"y":20,"z":20}},"name":"my-animation","description":"my-description","image":{"image":{},"src":"http://localhost:3137/assets/game/image/bricks/square_brick.png","domElement":{}},"src":"http://localhost:3137/assets/game/image/bricks/square_brick.png","domElement":{},"frameSize":{"x":85,"y":85,"z":0},"frameBounds":{"min":{"x":0,"y":0,"z":0},"max":{"x":0,"y":0,"z":0},"termPoint":{"x":0,"y":0,"z":0}},"frameOffset":{"x":0,"y":0,"z":0},"extras":false,"frames":[{"image":{"image":{},"src":"http://localhost:3137/assets/game/image/bricks/square_brick.png","domElement":{}},"frameSize":{"x":85,"y":85,"z":0},"framePos":{"x":0,"y":0}}],"flipX":false,"cix":0,"selected_frame":{"image":{"image":{},"src":"http://localhost:3137/assets/game/image/bricks/square_brick.png","domElement":{}},"frameSize":{"x":85,"y":85,"z":0},"framePos":{"x":0,"y":0}},"timer":0,"duration":1000,"seesaw_mode":false}],"motions":[],"projectiles":[],"sounds":[],"image":{"image":{},"src":"http://localhost:3137/assets/game/image/bricks/square_brick.png","domElement":{}},"size":{"x":40,"y":40,"z":0},"position":{"x":180,"y":4580,"z":0},"collision_bounds":{"min":{"x":0,"y":0,"z":0},"max":{"x":0,"y":0,"z":0}},"rotation":{"x":0,"y":0,"z":0},"selected_animation":{"defaultArgs":{"name":"my-animation","description":"my-description","frames":[],"type":"none","delay":0,"frameSize":{"x":44,"y":44,"z":0},"frameBounds":{"min":{"x":0,"y":0,"z":0},"max":{"x":0,"y":0,"z":0},"termPoint":{"x":0,"y":0,"z":0}},"frameOffset":{"x":0,"y":0,"z":0},"flipX":false,"duration":1000,"size":{"x":20,"y":20,"z":20}},"name":"my-animation","description":"my-description","image":{"image":{},"src":"http://localhost:3137/assets/game/image/bricks/square_brick.png","domElement":{}},"src":"http://localhost:3137/assets/game/image/bricks/square_brick.png","domElement":{},"frameSize":{"x":85,"y":85,"z":0},"frameBounds":{"min":{"x":0,"y":0,"z":0},"max":{"x":0,"y":0,"z":0},"termPoint":{"x":0,"y":0,"z":0}},"frameOffset":{"x":0,"y":0,"z":0},"extras":false,"frames":[{"image":{"image":{},"src":"http://localhost:3137/assets/game/image/bricks/square_brick.png","domElement":{}},"frameSize":{"x":85,"y":85,"z":0},"framePos":{"x":0,"y":0}}],"flipX":false,"cix":0,"selected_frame":{"image":{"image":{},"src":"http://localhost:3137/assets/game/image/bricks/square_brick.png","domElement":{}},"frameSize":{"x":85,"y":85,"z":0},"framePos":{"x":0,"y":0}},"timer":0,"duration":1000,"seesaw_mode":false},"speed":{"x":0,"y":0,"z":0},"acceleration":{"x":0,"y":0,"z":0},"rot_speed":{"x":0,"y":0,"z":0},"rot_accel":{"x":0,"y":0,"z":0},"padding":{"x":0,"y":0,"z":0},"tag":"brick_block","id":"a904dde0-8f75-4830-a879-34c5a5755d0c","hoverSelected":false,"hover_selected":false,"drag_selected":false,"selected":false},{"active":true,"name":"brick_block","description":"__","gravity":"medium","__initializers":[],"img":{},"src":"http://localhost:3137/assets/game/image/bricks/square_brick.png","__mapScale":false,"__mapSize":{"x":40,"y":40,"z":0},"frameSize":{"x":85,"y":85,"z":0},"type":"basic","animations":[{"defaultArgs":{"name":"my-animation","description":"my-description","frames":[],"type":"none","delay":0,"frameSize":{"x":44,"y":44,"z":0},"frameBounds":{"min":{"x":0,"y":0,"z":0},"max":{"x":0,"y":0,"z":0},"termPoint":{"x":0,"y":0,"z":0}},"frameOffset":{"x":0,"y":0,"z":0},"flipX":false,"duration":1000,"size":{"x":20,"y":20,"z":20}},"name":"my-animation","description":"my-description","image":{"image":{},"src":"http://localhost:3137/assets/game/image/bricks/square_brick.png","domElement":{}},"src":"http://localhost:3137/assets/game/image/bricks/square_brick.png","domElement":{},"frameSize":{"x":85,"y":85,"z":0},"frameBounds":{"min":{"x":0,"y":0,"z":0},"max":{"x":0,"y":0,"z":0},"termPoint":{"x":0,"y":0,"z":0}},"frameOffset":{"x":0,"y":0,"z":0},"extras":false,"frames":[{"image":{"image":{},"src":"http://localhost:3137/assets/game/image/bricks/square_brick.png","domElement":{}},"frameSize":{"x":85,"y":85,"z":0},"framePos":{"x":0,"y":0}}],"flipX":false,"cix":0,"selected_frame":{"image":{"image":{},"src":"http://localhost:3137/assets/game/image/bricks/square_brick.png","domElement":{}},"frameSize":{"x":85,"y":85,"z":0},"framePos":{"x":0,"y":0}},"timer":0,"duration":1000,"seesaw_mode":false}],"motions":[],"projectiles":[],"sounds":[],"image":{"image":{},"src":"http://localhost:3137/assets/game/image/bricks/square_brick.png","domElement":{}},"size":{"x":40,"y":40,"z":0},"position":{"x":280,"y":4680,"z":0},"collision_bounds":{"min":{"x":0,"y":0,"z":0},"max":{"x":0,"y":0,"z":0}},"rotation":{"x":0,"y":0,"z":0},"selected_animation":{"defaultArgs":{"name":"my-animation","description":"my-description","frames":[],"type":"none","delay":0,"frameSize":{"x":44,"y":44,"z":0},"frameBounds":{"min":{"x":0,"y":0,"z":0},"max":{"x":0,"y":0,"z":0},"termPoint":{"x":0,"y":0,"z":0}},"frameOffset":{"x":0,"y":0,"z":0},"flipX":false,"duration":1000,"size":{"x":20,"y":20,"z":20}},"name":"my-animation","description":"my-description","image":{"image":{},"src":"http://localhost:3137/assets/game/image/bricks/square_brick.png","domElement":{}},"src":"http://localhost:3137/assets/game/image/bricks/square_brick.png","domElement":{},"frameSize":{"x":85,"y":85,"z":0},"frameBounds":{"min":{"x":0,"y":0,"z":0},"max":{"x":0,"y":0,"z":0},"termPoint":{"x":0,"y":0,"z":0}},"frameOffset":{"x":0,"y":0,"z":0},"extras":false,"frames":[{"image":{"image":{},"src":"http://localhost:3137/assets/game/image/bricks/square_brick.png","domElement":{}},"frameSize":{"x":85,"y":85,"z":0},"framePos":{"x":0,"y":0}}],"flipX":false,"cix":0,"selected_frame":{"image":{"image":{},"src":"http://localhost:3137/assets/game/image/bricks/square_brick.png","domElement":{}},"frameSize":{"x":85,"y":85,"z":0},"framePos":{"x":0,"y":0}},"timer":0,"duration":1000,"seesaw_mode":false},"speed":{"x":0,"y":0,"z":0},"acceleration":{"x":0,"y":0,"z":0},"rot_speed":{"x":0,"y":0,"z":0},"rot_accel":{"x":0,"y":0,"z":0},"padding":{"x":0,"y":0,"z":0},"tag":"brick_block","id":"79358d66-c3cd-4e87-b23b-54b0352a532a","hoverSelected":false,"hover_selected":false,"drag_selected":false,"selected":false},{"active":true,"name":"brick_block","description":"__","gravity":"medium","__initializers":[],"img":{},"src":"http://localhost:3137/assets/game/image/bricks/square_brick.png","__mapScale":false,"__mapSize":{"x":40,"y":40,"z":0},"frameSize":{"x":85,"y":85,"z":0},"type":"basic","animations":[{"defaultArgs":{"name":"my-animation","description":"my-description","frames":[],"type":"none","delay":0,"frameSize":{"x":44,"y":44,"z":0},"frameBounds":{"min":{"x":0,"y":0,"z":0},"max":{"x":0,"y":0,"z":0},"termPoint":{"x":0,"y":0,"z":0}},"frameOffset":{"x":0,"y":0,"z":0},"flipX":false,"duration":1000,"size":{"x":20,"y":20,"z":20}},"name":"my-animation","description":"my-description","image":{"image":{},"src":"http://localhost:3137/assets/game/image/bricks/square_brick.png","domElement":{}},"src":"http://localhost:3137/assets/game/image/bricks/square_brick.png","domElement":{},"frameSize":{"x":85,"y":85,"z":0},"frameBounds":{"min":{"x":0,"y":0,"z":0},"max":{"x":0,"y":0,"z":0},"termPoint":{"x":0,"y":0,"z":0}},"frameOffset":{"x":0,"y":0,"z":0},"extras":false,"frames":[{"image":{"image":{},"src":"http://localhost:3137/assets/game/image/bricks/square_brick.png","domElement":{}},"frameSize":{"x":85,"y":85,"z":0},"framePos":{"x":0,"y":0}}],"flipX":false,"cix":0,"selected_frame":{"image":{"image":{},"src":"http://localhost:3137/assets/game/image/bricks/square_brick.png","domElement":{}},"frameSize":{"x":85,"y":85,"z":0},"framePos":{"x":0,"y":0}},"timer":0,"duration":1000,"seesaw_mode":false}],"motions":[],"projectiles":[],"sounds":[],"image":{"image":{},"src":"http://localhost:3137/assets/game/image/bricks/square_brick.png","domElement":{}},"size":{"x":40,"y":40,"z":0},"position":{"x":180,"y":4480,"z":0},"collision_bounds":{"min":{"x":0,"y":0,"z":0},"max":{"x":0,"y":0,"z":0}},"rotation":{"x":0,"y":0,"z":0},"selected_animation":{"defaultArgs":{"name":"my-animation","description":"my-description","frames":[],"type":"none","delay":0,"frameSize":{"x":44,"y":44,"z":0},"frameBounds":{"min":{"x":0,"y":0,"z":0},"max":{"x":0,"y":0,"z":0},"termPoint":{"x":0,"y":0,"z":0}},"frameOffset":{"x":0,"y":0,"z":0},"flipX":false,"duration":1000,"size":{"x":20,"y":20,"z":20}},"name":"my-animation","description":"my-description","image":{"image":{},"src":"http://localhost:3137/assets/game/image/bricks/square_brick.png","domElement":{}},"src":"http://localhost:3137/assets/game/image/bricks/square_brick.png","domElement":{},"frameSize":{"x":85,"y":85,"z":0},"frameBounds":{"min":{"x":0,"y":0,"z":0},"max":{"x":0,"y":0,"z":0},"termPoint":{"x":0,"y":0,"z":0}},"frameOffset":{"x":0,"y":0,"z":0},"extras":false,"frames":[{"image":{"image":{},"src":"http://localhost:3137/assets/game/image/bricks/square_brick.png","domElement":{}},"frameSize":{"x":85,"y":85,"z":0},"framePos":{"x":0,"y":0}}],"flipX":false,"cix":0,"selected_frame":{"image":{"image":{},"src":"http://localhost:3137/assets/game/image/bricks/square_brick.png","domElement":{}},"frameSize":{"x":85,"y":85,"z":0},"framePos":{"x":0,"y":0}},"timer":0,"duration":1000,"seesaw_mode":false},"speed":{"x":0,"y":0,"z":0},"acceleration":{"x":0,"y":0,"z":0},"rot_speed":{"x":0,"y":0,"z":0},"rot_accel":{"x":0,"y":0,"z":0},"padding":{"x":0,"y":0,"z":0},"tag":"brick_block","id":"662df94d-f3c6-47d5-950f-5403c3a26f83","hoverSelected":false,"hover_selected":false,"drag_selected":false,"selected":false},{"active":true,"name":"brick_block","description":"__","gravity":"medium","__initializers":[],"img":{},"src":"http://localhost:3137/assets/game/image/bricks/square_brick.png","__mapScale":false,"__mapSize":{"x":40,"y":40,"z":0},"frameSize":{"x":85,"y":85,"z":0},"type":"basic","animations":[{"defaultArgs":{"name":"my-animation","description":"my-description","frames":[],"type":"none","delay":0,"frameSize":{"x":44,"y":44,"z":0},"frameBounds":{"min":{"x":0,"y":0,"z":0},"max":{"x":0,"y":0,"z":0},"termPoint":{"x":0,"y":0,"z":0}},"frameOffset":{"x":0,"y":0,"z":0},"flipX":false,"duration":1000,"size":{"x":20,"y":20,"z":20}},"name":"my-animation","description":"my-description","image":{"image":{},"src":"http://localhost:3137/assets/game/image/bricks/square_brick.png","domElement":{}},"src":"http://localhost:3137/assets/game/image/bricks/square_brick.png","domElement":{},"frameSize":{"x":85,"y":85,"z":0},"frameBounds":{"min":{"x":0,"y":0,"z":0},"max":{"x":0,"y":0,"z":0},"termPoint":{"x":0,"y":0,"z":0}},"frameOffset":{"x":0,"y":0,"z":0},"extras":false,"frames":[{"image":{"image":{},"src":"http://localhost:3137/assets/game/image/bricks/square_brick.png","domElement":{}},"frameSize":{"x":85,"y":85,"z":0},"framePos":{"x":0,"y":0}}],"flipX":false,"cix":0,"selected_frame":{"image":{"image":{},"src":"http://localhost:3137/assets/game/image/bricks/square_brick.png","domElement":{}},"frameSize":{"x":85,"y":85,"z":0},"framePos":{"x":0,"y":0}},"timer":0,"duration":1000,"seesaw_mode":false}],"motions":[],"projectiles":[],"sounds":[],"image":{"image":{},"src":"http://localhost:3137/assets/game/image/bricks/square_brick.png","domElement":{}},"size":{"x":40,"y":40,"z":0},"position":{"x":80,"y":4430,"z":0},"collision_bounds":{"min":{"x":0,"y":0,"z":0},"max":{"x":0,"y":0,"z":0}},"rotation":{"x":0,"y":0,"z":0},"selected_animation":{"defaultArgs":{"name":"my-animation","description":"my-description","frames":[],"type":"none","delay":0,"frameSize":{"x":44,"y":44,"z":0},"frameBounds":{"min":{"x":0,"y":0,"z":0},"max":{"x":0,"y":0,"z":0},"termPoint":{"x":0,"y":0,"z":0}},"frameOffset":{"x":0,"y":0,"z":0},"flipX":false,"duration":1000,"size":{"x":20,"y":20,"z":20}},"name":"my-animation","description":"my-description","image":{"image":{},"src":"http://localhost:3137/assets/game/image/bricks/square_brick.png","domElement":{}},"src":"http://localhost:3137/assets/game/image/bricks/square_brick.png","domElement":{},"frameSize":{"x":85,"y":85,"z":0},"frameBounds":{"min":{"x":0,"y":0,"z":0},"max":{"x":0,"y":0,"z":0},"termPoint":{"x":0,"y":0,"z":0}},"frameOffset":{"x":0,"y":0,"z":0},"extras":false,"frames":[{"image":{"image":{},"src":"http://localhost:3137/assets/game/image/bricks/square_brick.png","domElement":{}},"frameSize":{"x":85,"y":85,"z":0},"framePos":{"x":0,"y":0}}],"flipX":false,"cix":0,"selected_frame":{"image":{"image":{},"src":"http://localhost:3137/assets/game/image/bricks/square_brick.png","domElement":{}},"frameSize":{"x":85,"y":85,"z":0},"framePos":{"x":0,"y":0}},"timer":0,"duration":1000,"seesaw_mode":false},"speed":{"x":0,"y":0,"z":0},"acceleration":{"x":0,"y":0,"z":0},"rot_speed":{"x":0,"y":0,"z":0},"rot_accel":{"x":0,"y":0,"z":0},"padding":{"x":0,"y":0,"z":0},"tag":"brick_block","id":"81c25d45-d6b1-4751-896c-30b3da1e9c57","hoverSelected":false,"hover_selected":false,"drag_selected":false,"selected":false},{"active":true,"name":"brick_block","description":"__","gravity":"medium","__initializers":[],"img":{},"src":"http://localhost:3137/assets/game/image/bricks/square_brick.png","__mapScale":false,"__mapSize":{"x":40,"y":40,"z":0},"frameSize":{"x":85,"y":85,"z":0},"type":"basic","animations":[{"defaultArgs":{"name":"my-animation","description":"my-description","frames":[],"type":"none","delay":0,"frameSize":{"x":44,"y":44,"z":0},"frameBounds":{"min":{"x":0,"y":0,"z":0},"max":{"x":0,"y":0,"z":0},"termPoint":{"x":0,"y":0,"z":0}},"frameOffset":{"x":0,"y":0,"z":0},"flipX":false,"duration":1000,"size":{"x":20,"y":20,"z":20}},"name":"my-animation","description":"my-description","image":{"image":{},"src":"http://localhost:3137/assets/game/image/bricks/square_brick.png","domElement":{}},"src":"http://localhost:3137/assets/game/image/bricks/square_brick.png","domElement":{},"frameSize":{"x":85,"y":85,"z":0},"frameBounds":{"min":{"x":0,"y":0,"z":0},"max":{"x":0,"y":0,"z":0},"termPoint":{"x":0,"y":0,"z":0}},"frameOffset":{"x":0,"y":0,"z":0},"extras":false,"frames":[{"image":{"image":{},"src":"http://localhost:3137/assets/game/image/bricks/square_brick.png","domElement":{}},"frameSize":{"x":85,"y":85,"z":0},"framePos":{"x":0,"y":0}}],"flipX":false,"cix":0,"selected_frame":{"image":{"image":{},"src":"http://localhost:3137/assets/game/image/bricks/square_brick.png","domElement":{}},"frameSize":{"x":85,"y":85,"z":0},"framePos":{"x":0,"y":0}},"timer":0,"duration":1000,"seesaw_mode":false}],"motions":[],"projectiles":[],"sounds":[],"image":{"image":{},"src":"http://localhost:3137/assets/game/image/bricks/square_brick.png","domElement":{}},"size":{"x":40,"y":40,"z":0},"position":{"x":180,"y":4330,"z":0},"collision_bounds":{"min":{"x":0,"y":0,"z":0},"max":{"x":0,"y":0,"z":0}},"rotation":{"x":0,"y":0,"z":0},"selected_animation":{"defaultArgs":{"name":"my-animation","description":"my-description","frames":[],"type":"none","delay":0,"frameSize":{"x":44,"y":44,"z":0},"frameBounds":{"min":{"x":0,"y":0,"z":0},"max":{"x":0,"y":0,"z":0},"termPoint":{"x":0,"y":0,"z":0}},"frameOffset":{"x":0,"y":0,"z":0},"flipX":false,"duration":1000,"size":{"x":20,"y":20,"z":20}},"name":"my-animation","description":"my-description","image":{"image":{},"src":"http://localhost:3137/assets/game/image/bricks/square_brick.png","domElement":{}},"src":"http://localhost:3137/assets/game/image/bricks/square_brick.png","domElement":{},"frameSize":{"x":85,"y":85,"z":0},"frameBounds":{"min":{"x":0,"y":0,"z":0},"max":{"x":0,"y":0,"z":0},"termPoint":{"x":0,"y":0,"z":0}},"frameOffset":{"x":0,"y":0,"z":0},"extras":false,"frames":[{"image":{"image":{},"src":"http://localhost:3137/assets/game/image/bricks/square_brick.png","domElement":{}},"frameSize":{"x":85,"y":85,"z":0},"framePos":{"x":0,"y":0}}],"flipX":false,"cix":0,"selected_frame":{"image":{"image":{},"src":"http://localhost:3137/assets/game/image/bricks/square_brick.png","domElement":{}},"frameSize":{"x":85,"y":85,"z":0},"framePos":{"x":0,"y":0}},"timer":0,"duration":1000,"seesaw_mode":false},"speed":{"x":0,"y":0,"z":0},"acceleration":{"x":0,"y":0,"z":0},"rot_speed":{"x":0,"y":0,"z":0},"rot_accel":{"x":0,"y":0,"z":0},"padding":{"x":0,"y":0,"z":0},"tag":"brick_block","id":"bfcb4449-1101-44a6-bcdb-a0a9ec68295f","hoverSelected":false,"hover_selected":false,"drag_selected":false,"selected":false}],"settings":{"name":"myLevel.json","description":"the default level for this game","pixelSnapX":50,"pixelSnapY":50,"levelSizeX":5000,"levelSizeY":5000,"levelSizeZ":0,"gameScale":2,"testGravity":"TODO","testPlayer":"TODO","psuedoSpriteTypes":["player","enemy","background","interactive"],"psuedoAnimationTypes":{"attack_0":"System.attack_0","attack_1":"System.attack_1","attack_2":"System.attack_2","attack_3":"System.attack_3","attack_4":"System.attack_4","defend_0":"System.defend_0","defend_1":"System.defend_1","defend_2":"System.defend_2","defend_3":"System.defend_3","defend_4":"System.defend_4","heal_0":"System.heal_0","heal_1":"System.heal_1","heal_2":"System.heal_2","heal_3":"System.heal_3","heal_4":"System.heal_4"}},"gameWindow":[]}